<?xml version="1.0" encoding="utf-8" ?>
<ogr:FeatureCollection
     xmlns:xsi="http://www.w3c.org/2001/XMLSchema-instance"
     xsi:schemaLocation=". dlinks.xsd"
     xmlns:ogr="http://ogr.maptools.org/"
     xmlns:gml="http://www.opengis.net/gml">
  <gml:boundedBy>
    <gml:Box>
<gml:coord><gml:X>2.199479</gml:X><gml:Y>41.853904</gml:Y></gml:coord>
<gml:coord><gml:X>2.284266</gml:X><gml:Y>41.936632</gml:Y></gml:coord>
   </gml:Box>
</gml:boundedBy>
          <gml:featureMember>
          <dlinks fid="3311">
          <NODE1_ID>1592</NODE1_ID>
          <NODE1_NAME>MallaSerrat</NODE1_NAME>
          <NODE2_ID>4297</NODE2_ID>
          <NODE2_NAME>VicLluis</NODE2_NAME>
          <KMS>3.976</KMS>
          <LINK_TYPE>ap/client</LINK_TYPE>
          <STATUS>Working</STATUS>
          <ogr:geometryProperty><gml:LineString><gml:coordinates>2.233511,41.887250 2.255504,41.919056</gml:coordinates></gml:LineString></ogr:geometryProperty>
          </dlinks>
          </gml:featureMember>
          <gml:featureMember>
          <dlinks fid="6181">
          <NODE1_ID>7052</NODE1_ID>
          <NODE1_NAME>VicSantMarc</NODE1_NAME>
          <NODE2_ID>1711</NODE2_ID>
          <NODE2_NAME>VicHabitat</NODE2_NAME>
          <KMS>1.288</KMS>
          <LINK_TYPE>ap/client</LINK_TYPE>
          <STATUS>Working</STATUS>
          <ogr:geometryProperty><gml:LineString><gml:coordinates>2.256780,41.918000 2.249722,41.928333</gml:coordinates></gml:LineString></ogr:geometryProperty>
          </dlinks>
          </gml:featureMember>
          <gml:featureMember>
          <dlinks fid="8937">
          <NODE1_ID>11317</NODE1_ID>
          <NODE1_NAME>VicSolruf</NODE1_NAME>
          <NODE2_ID>7859</NODE2_ID>
          <NODE2_NAME>GXACampanar</NODE2_NAME>
          <KMS>2.437</KMS>
          <LINK_TYPE>ap/client</LINK_TYPE>
          <STATUS>Working</STATUS>
          <ogr:geometryProperty><gml:LineString><gml:coordinates>2.256448,41.918865 2.227957,41.913525</gml:coordinates></gml:LineString></ogr:geometryProperty>
          </dlinks>
          </gml:featureMember>
          <gml:featureMember>
          <dlinks fid="9678">
          <NODE1_ID>13345</NODE1_ID>
          <NODE1_NAME>VicSerafiM</NODE1_NAME>
          <NODE2_ID>7344</NODE2_ID>
          <NODE2_NAME>VicSSebastia</NODE2_NAME>
          <KMS>4.844</KMS>
          <LINK_TYPE>ap/client</LINK_TYPE>
          <STATUS>Working</STATUS>
          <ogr:geometryProperty><gml:LineString><gml:coordinates>2.257244,41.919587 2.199479,41.925987</gml:coordinates></gml:LineString></ogr:geometryProperty>
          </dlinks>
          </gml:featureMember>
          <gml:featureMember>
          <dlinks fid="10176">
          <NODE1_ID>6372</NODE1_ID>
          <NODE1_NAME>VicMasRiera</NODE1_NAME>
          <NODE2_ID>1641</NODE2_ID>
          <NODE2_NAME>VicPlacaEloi</NODE2_NAME>
          <KMS>2.127</KMS>
          <LINK_TYPE>ap/client</LINK_TYPE>
          <STATUS>Working</STATUS>
          <ogr:geometryProperty><gml:LineString><gml:coordinates>2.254187,41.911183 2.255099,41.930320</gml:coordinates></gml:LineString></ogr:geometryProperty>
          </dlinks>
          </gml:featureMember>
          <gml:featureMember>
          <dlinks fid="11113">
          <NODE1_ID>15035</NODE1_ID>
          <NODE1_NAME>VicPalauBojons</NODE1_NAME>
          <NODE2_ID>15036</NODE2_ID>
          <NODE2_NAME>VicSSantFerm</NODE2_NAME>
          <KMS>1.71</KMS>
          <LINK_TYPE>wds</LINK_TYPE>
          <STATUS>Working</STATUS>
          <ogr:geometryProperty><gml:LineString><gml:coordinates>2.257728,41.929168 2.256746,41.913791</gml:coordinates></gml:LineString></ogr:geometryProperty>
          </dlinks>
          </gml:featureMember>
          <gml:featureMember>
          <dlinks fid="11185">
          <NODE1_ID>1638</NODE1_ID>
          <NODE1_NAME>VicSeminari</NODE1_NAME>
          <NODE2_ID>1655</NODE2_ID>
          <NODE2_NAME>VicBarriOsona</NODE2_NAME>
          <KMS>2.354</KMS>
          <LINK_TYPE>wds</LINK_TYPE>
          <STATUS>Working</STATUS>
          <ogr:geometryProperty><gml:LineString><gml:coordinates>2.257261,41.936632 2.260303,41.915561</gml:coordinates></gml:LineString></ogr:geometryProperty>
          </dlinks>
          </gml:featureMember>
          <gml:featureMember>
          <dlinks fid="11224">
          <NODE1_ID>12411</NODE1_ID>
          <NODE1_NAME>Vicjordistferm</NODE1_NAME>
          <NODE2_ID>15036</NODE2_ID>
          <NODE2_NAME>VicSSantFerm</NODE2_NAME>
          <KMS>0.025</KMS>
          <LINK_TYPE>ap/client</LINK_TYPE>
          <STATUS>Working</STATUS>
          <ogr:geometryProperty><gml:LineString><gml:coordinates>2.256682,41.913567 2.256746,41.913791</gml:coordinates></gml:LineString></ogr:geometryProperty>
          </dlinks>
          </gml:featureMember>
          <gml:featureMember>
          <dlinks fid="11275">
          <NODE1_ID>15036</NODE1_ID>
          <NODE1_NAME>VicSSantFerm</NODE1_NAME>
          <NODE2_ID>15027</NODE2_ID>
          <NODE2_NAME>VicPares</NODE2_NAME>
          <KMS>0.112</KMS>
          <LINK_TYPE>ap/client</LINK_TYPE>
          <STATUS>Working</STATUS>
          <ogr:geometryProperty><gml:LineString><gml:coordinates>2.256746,41.913791 2.256807,41.912784</gml:coordinates></gml:LineString></ogr:geometryProperty>
          </dlinks>
          </gml:featureMember>
          <gml:featureMember>
          <dlinks fid="11442">
          <NODE1_ID>15290</NODE1_ID>
          <NODE1_NAME>VicMAlemany</NODE1_NAME>
          <NODE2_ID>15036</NODE2_ID>
          <NODE2_NAME>VicSSantFerm</NODE2_NAME>
          <KMS>0.542</KMS>
          <LINK_TYPE>ap/client</LINK_TYPE>
          <STATUS>Working</STATUS>
          <ogr:geometryProperty><gml:LineString><gml:coordinates>2.253933,41.918200 2.256746,41.913791</gml:coordinates></gml:LineString></ogr:geometryProperty>
          </dlinks>
          </gml:featureMember>
          <gml:featureMember>
          <dlinks fid="11446">
          <NODE1_ID>15036</NODE1_ID>
          <NODE1_NAME>VicSSantFerm</NODE1_NAME>
          <NODE2_ID>1854</NODE2_ID>
          <NODE2_NAME>VicJC-Informatica</NODE2_NAME>
          <KMS>1.151</KMS>
          <LINK_TYPE>ap/client</LINK_TYPE>
          <STATUS>Working</STATUS>
          <ogr:geometryProperty><gml:LineString><gml:coordinates>2.256746,41.913791 2.256588,41.924149</gml:coordinates></gml:LineString></ogr:geometryProperty>
          </dlinks>
          </gml:featureMember>
          <gml:featureMember>
          <dlinks fid="11544">
          <NODE1_ID>12169</NODE1_ID>
          <NODE1_NAME>VicMontserratM</NODE1_NAME>
          <NODE2_ID>15036</NODE2_ID>
          <NODE2_NAME>VicSSantFerm</NODE2_NAME>
          <KMS>0.089</KMS>
          <LINK_TYPE>ap/client</LINK_TYPE>
          <STATUS>Working</STATUS>
          <ogr:geometryProperty><gml:LineString><gml:coordinates>2.257192,41.913059 2.256746,41.913791</gml:coordinates></gml:LineString></ogr:geometryProperty>
          </dlinks>
          </gml:featureMember>
          <gml:featureMember>
          <dlinks fid="12050">
          <NODE1_ID>15036</NODE1_ID>
          <NODE1_NAME>VicSSantFerm</NODE1_NAME>
          <NODE2_ID>15929</NODE2_ID>
          <NODE2_NAME>VicMariaDolorsSola</NODE2_NAME>
          <KMS>0.555</KMS>
          <LINK_TYPE>ap/client</LINK_TYPE>
          <STATUS>Working</STATUS>
          <ogr:geometryProperty><gml:LineString><gml:coordinates>2.256746,41.913791 2.258824,41.918542</gml:coordinates></gml:LineString></ogr:geometryProperty>
          </dlinks>
          </gml:featureMember>
          <gml:featureMember>
          <dlinks fid="12079">
          <NODE1_ID>12217</NODE1_ID>
          <NODE1_NAME>VicCastro</NODE1_NAME>
          <NODE2_ID>15036</NODE2_ID>
          <NODE2_NAME>VicSSantFerm</NODE2_NAME>
          <KMS>0.053</KMS>
          <LINK_TYPE>ap/client</LINK_TYPE>
          <STATUS>Working</STATUS>
          <ogr:geometryProperty><gml:LineString><gml:coordinates>2.256199,41.913547 2.256746,41.913791</gml:coordinates></gml:LineString></ogr:geometryProperty>
          </dlinks>
          </gml:featureMember>
          <gml:featureMember>
          <dlinks fid="12096">
          <NODE1_ID>15036</NODE1_ID>
          <NODE1_NAME>VicSSantFerm</NODE1_NAME>
          <NODE2_ID>12554</NODE2_ID>
          <NODE2_NAME>VicComasQuintana</NODE2_NAME>
          <KMS>0.467</KMS>
          <LINK_TYPE>ap/client</LINK_TYPE>
          <STATUS>Working</STATUS>
          <ogr:geometryProperty><gml:LineString><gml:coordinates>2.256746,41.913791 2.257459,41.917959</gml:coordinates></gml:LineString></ogr:geometryProperty>
          </dlinks>
          </gml:featureMember>
          <gml:featureMember>
          <dlinks fid="12182">
          <NODE1_ID>15036</NODE1_ID>
          <NODE1_NAME>VicSSantFerm</NODE1_NAME>
          <NODE2_ID>15913</NODE2_ID>
          <NODE2_NAME>VicSantaAnna</NODE2_NAME>
          <KMS>1.208</KMS>
          <LINK_TYPE>ap/client</LINK_TYPE>
          <STATUS>Working</STATUS>
          <ogr:geometryProperty><gml:LineString><gml:coordinates>2.256746,41.913791 2.261111,41.924167</gml:coordinates></gml:LineString></ogr:geometryProperty>
          </dlinks>
          </gml:featureMember>
          <gml:featureMember>
          <dlinks fid="12192">
          <NODE1_ID>16085</NODE1_ID>
          <NODE1_NAME>VicJmiro</NODE1_NAME>
          <NODE2_ID>4332</NODE2_ID>
          <NODE2_NAME>SEBTeatre</NODE2_NAME>
          <KMS>2.472</KMS>
          <LINK_TYPE>ap/client</LINK_TYPE>
          <STATUS>Working</STATUS>
          <ogr:geometryProperty><gml:LineString><gml:coordinates>2.260227,41.914493 2.284266,41.901338</gml:coordinates></gml:LineString></ogr:geometryProperty>
          </dlinks>
          </gml:featureMember>
          <gml:featureMember>
          <dlinks fid="12363">
          <NODE1_ID>15036</NODE1_ID>
          <NODE1_NAME>VicSSantFerm</NODE1_NAME>
          <NODE2_ID>16106</NODE2_ID>
          <NODE2_NAME>VicShanti</NODE2_NAME>
          <KMS>0.111</KMS>
          <LINK_TYPE>ap/client</LINK_TYPE>
          <STATUS>Working</STATUS>
          <ogr:geometryProperty><gml:LineString><gml:coordinates>2.256746,41.913791 2.255556,41.913333</gml:coordinates></gml:LineString></ogr:geometryProperty>
          </dlinks>
          </gml:featureMember>
          <gml:featureMember>
          <dlinks fid="12454">
          <NODE1_ID>16314</NODE1_ID>
          <NODE1_NAME>VicAbdelkarimE</NODE1_NAME>
          <NODE2_ID>15036</NODE2_ID>
          <NODE2_NAME>VicSSantFerm</NODE2_NAME>
          <KMS>0.949</KMS>
          <LINK_TYPE>ap/client</LINK_TYPE>
          <STATUS>Working</STATUS>
          <ogr:geometryProperty><gml:LineString><gml:coordinates>2.254562,41.922175 2.256746,41.913791</gml:coordinates></gml:LineString></ogr:geometryProperty>
          </dlinks>
          </gml:featureMember>
          <gml:featureMember>
          <dlinks fid="12713">
          <NODE1_ID>6408</NODE1_ID>
          <NODE1_NAME>VicGuga</NODE1_NAME>
          <NODE2_ID>15036</NODE2_ID>
          <NODE2_NAME>VicSSantFerm</NODE2_NAME>
          <KMS>0.729</KMS>
          <LINK_TYPE>ap/client</LINK_TYPE>
          <STATUS>Working</STATUS>
          <ogr:geometryProperty><gml:LineString><gml:coordinates>2.254820,41.920197 2.256746,41.913791</gml:coordinates></gml:LineString></ogr:geometryProperty>
          </dlinks>
          </gml:featureMember>
          <gml:featureMember>
          <dlinks fid="12929">
          <NODE1_ID>16927</NODE1_ID>
          <NODE1_NAME>VicMujerSagrada</NODE1_NAME>
          <NODE2_ID>15036</NODE2_ID>
          <NODE2_NAME>VicSSantFerm</NODE2_NAME>
          <KMS>0.103</KMS>
          <LINK_TYPE>ap/client</LINK_TYPE>
          <STATUS>Working</STATUS>
          <ogr:geometryProperty><gml:LineString><gml:coordinates>2.255553,41.913548 2.256746,41.913791</gml:coordinates></gml:LineString></ogr:geometryProperty>
          </dlinks>
          </gml:featureMember>
          <gml:featureMember>
          <dlinks fid="12966">
          <NODE1_ID>16991</NODE1_ID>
          <NODE1_NAME>VicAbdelaziz</NODE1_NAME>
          <NODE2_ID>15036</NODE2_ID>
          <NODE2_NAME>VicSSantFerm</NODE2_NAME>
          <KMS>0.146</KMS>
          <LINK_TYPE>ap/client</LINK_TYPE>
          <STATUS>Working</STATUS>
          <ogr:geometryProperty><gml:LineString><gml:coordinates>2.257867,41.912777 2.256746,41.913791</gml:coordinates></gml:LineString></ogr:geometryProperty>
          </dlinks>
          </gml:featureMember>
          <gml:featureMember>
          <dlinks fid="12967">
          <NODE1_ID>16992</NODE1_ID>
          <NODE1_NAME>VicJudithP</NODE1_NAME>
          <NODE2_ID>4332</NODE2_ID>
          <NODE2_NAME>SEBTeatre</NODE2_NAME>
          <KMS>2.509</KMS>
          <LINK_TYPE>ap/client</LINK_TYPE>
          <STATUS>Working</STATUS>
          <ogr:geometryProperty><gml:LineString><gml:coordinates>2.260362,41.915172 2.284266,41.901338</gml:coordinates></gml:LineString></ogr:geometryProperty>
          </dlinks>
          </gml:featureMember>
          <gml:featureMember>
          <dlinks fid="13316">
          <NODE1_ID>17479</NODE1_ID>
          <NODE1_NAME>VicAlexSalomo</NODE1_NAME>
          <NODE2_ID>15036</NODE2_ID>
          <NODE2_NAME>VicSSantFerm</NODE2_NAME>
          <KMS>1.742</KMS>
          <LINK_TYPE>ap/client</LINK_TYPE>
          <STATUS>Working</STATUS>
          <ogr:geometryProperty><gml:LineString><gml:coordinates>2.264358,41.928412 2.256746,41.913791</gml:coordinates></gml:LineString></ogr:geometryProperty>
          </dlinks>
          </gml:featureMember>
          <gml:featureMember>
          <dlinks fid="13376">
          <NODE1_ID>17555</NODE1_ID>
          <NODE1_NAME>VicOmniumJaume</NODE1_NAME>
          <NODE2_ID>15036</NODE2_ID>
          <NODE2_NAME>VicSSantFerm</NODE2_NAME>
          <KMS>0.316</KMS>
          <LINK_TYPE>ap/client</LINK_TYPE>
          <STATUS>Working</STATUS>
          <ogr:geometryProperty><gml:LineString><gml:coordinates>2.258629,41.916264 2.256746,41.913791</gml:coordinates></gml:LineString></ogr:geometryProperty>
          </dlinks>
          </gml:featureMember>
          <gml:featureMember>
          <dlinks fid="13759">
          <NODE1_ID>18072</NODE1_ID>
          <NODE1_NAME>VicSilviaM</NODE1_NAME>
          <NODE2_ID>15036</NODE2_ID>
          <NODE2_NAME>VicSSantFerm</NODE2_NAME>
          <KMS>0.855</KMS>
          <LINK_TYPE>ap/client</LINK_TYPE>
          <STATUS>Working</STATUS>
          <ogr:geometryProperty><gml:LineString><gml:coordinates>2.250803,41.920075 2.256746,41.913791</gml:coordinates></gml:LineString></ogr:geometryProperty>
          </dlinks>
          </gml:featureMember>
          <gml:featureMember>
          <dlinks fid="13893">
          <NODE1_ID>18235</NODE1_ID>
          <NODE1_NAME>VicRamonP</NODE1_NAME>
          <NODE2_ID>15036</NODE2_ID>
          <NODE2_NAME>VicSSantFerm</NODE2_NAME>
          <KMS>0.674</KMS>
          <LINK_TYPE>ap/client</LINK_TYPE>
          <STATUS>Working</STATUS>
          <ogr:geometryProperty><gml:LineString><gml:coordinates>2.257175,41.919850 2.256746,41.913791</gml:coordinates></gml:LineString></ogr:geometryProperty>
          </dlinks>
          </gml:featureMember>
          <gml:featureMember>
          <dlinks fid="14174">
          <NODE1_ID>11810</NODE1_ID>
          <NODE1_NAME>VicSaid</NODE1_NAME>
          <NODE2_ID>15036</NODE2_ID>
          <NODE2_NAME>VicSSantFerm</NODE2_NAME>
          <KMS>0.915</KMS>
          <LINK_TYPE>ap/client</LINK_TYPE>
          <STATUS>Working</STATUS>
          <ogr:geometryProperty><gml:LineString><gml:coordinates>2.249883,41.920243 2.256746,41.913791</gml:coordinates></gml:LineString></ogr:geometryProperty>
          </dlinks>
          </gml:featureMember>
          <gml:featureMember>
          <dlinks fid="14719">
          <NODE1_ID>7182</NODE1_ID>
          <NODE1_NAME>VicRemeiNuriaA</NODE1_NAME>
          <NODE2_ID>15036</NODE2_ID>
          <NODE2_NAME>VicSSantFerm</NODE2_NAME>
          <KMS>0.957</KMS>
          <LINK_TYPE>ap/client</LINK_TYPE>
          <STATUS>Working</STATUS>
          <ogr:geometryProperty><gml:LineString><gml:coordinates>2.249713,41.920620 2.256746,41.913791</gml:coordinates></gml:LineString></ogr:geometryProperty>
          </dlinks>
          </gml:featureMember>
          <gml:featureMember>
          <dlinks fid="14735">
          <NODE1_ID>19160</NODE1_ID>
          <NODE1_NAME>Viccumeres</NODE1_NAME>
          <NODE2_ID>15036</NODE2_ID>
          <NODE2_NAME>VicSSantFerm</NODE2_NAME>
          <KMS>0.667</KMS>
          <LINK_TYPE>ap/client</LINK_TYPE>
          <STATUS>Working</STATUS>
          <ogr:geometryProperty><gml:LineString><gml:coordinates>2.255854,41.919756 2.256746,41.913791</gml:coordinates></gml:LineString></ogr:geometryProperty>
          </dlinks>
          </gml:featureMember>
          <gml:featureMember>
          <dlinks fid="15341">
          <NODE1_ID>2103</NODE1_ID>
          <NODE1_NAME>VicBacRoda</NODE1_NAME>
          <NODE2_ID>15036</NODE2_ID>
          <NODE2_NAME>VicSSantFerm</NODE2_NAME>
          <KMS>1.188</KMS>
          <LINK_TYPE>ap/client</LINK_TYPE>
          <STATUS>Working</STATUS>
          <ogr:geometryProperty><gml:LineString><gml:coordinates>2.261000,41.924000 2.256746,41.913791</gml:coordinates></gml:LineString></ogr:geometryProperty>
          </dlinks>
          </gml:featureMember>
          <gml:featureMember>
          <dlinks fid="15697">
          <NODE1_ID>12824</NODE1_ID>
          <NODE1_NAME>VicMDiaz</NODE1_NAME>
          <NODE2_ID>15036</NODE2_ID>
          <NODE2_NAME>VicSSantFerm</NODE2_NAME>
          <KMS>0.902</KMS>
          <LINK_TYPE>ap/client</LINK_TYPE>
          <STATUS>Working</STATUS>
          <ogr:geometryProperty><gml:LineString><gml:coordinates>2.257914,41.921867 2.256746,41.913791</gml:coordinates></gml:LineString></ogr:geometryProperty>
          </dlinks>
          </gml:featureMember>
          <gml:featureMember>
          <dlinks fid="15916">
          <NODE1_ID>9458</NODE1_ID>
          <NODE1_NAME>VicDosEstadi</NODE1_NAME>
          <NODE2_ID>15036</NODE2_ID>
          <NODE2_NAME>VicSSantFerm</NODE2_NAME>
          <KMS>0.761</KMS>
          <LINK_TYPE>ap/client</LINK_TYPE>
          <STATUS>Working</STATUS>
          <ogr:geometryProperty><gml:LineString><gml:coordinates>2.252870,41.920000 2.256746,41.913791</gml:coordinates></gml:LineString></ogr:geometryProperty>
          </dlinks>
          </gml:featureMember>
          <gml:featureMember>
          <dlinks fid="16825">
          <NODE1_ID>15036</NODE1_ID>
          <NODE1_NAME>VicSSantFerm</NODE1_NAME>
          <NODE2_ID>20387</NODE2_ID>
          <NODE2_NAME>VicOlgaH</NODE2_NAME>
          <KMS>1.079</KMS>
          <LINK_TYPE>ap/client</LINK_TYPE>
          <STATUS>Working</STATUS>
          <ogr:geometryProperty><gml:LineString><gml:coordinates>2.256746,41.913791 2.253841,41.923256</gml:coordinates></gml:LineString></ogr:geometryProperty>
          </dlinks>
          </gml:featureMember>
          <gml:featureMember>
          <dlinks fid="17073">
          <NODE1_ID>21676</NODE1_ID>
          <NODE1_NAME>VicCarmela</NODE1_NAME>
          <NODE2_ID>15036</NODE2_ID>
          <NODE2_NAME>VicSSantFerm</NODE2_NAME>
          <KMS>0.156</KMS>
          <LINK_TYPE>ap/client</LINK_TYPE>
          <STATUS>Working</STATUS>
          <ogr:geometryProperty><gml:LineString><gml:coordinates>2.256441,41.912403 2.256746,41.913791</gml:coordinates></gml:LineString></ogr:geometryProperty>
          </dlinks>
          </gml:featureMember>
          <gml:featureMember>
          <dlinks fid="17273">
          <NODE1_ID>8187</NODE1_ID>
          <NODE1_NAME>VicTolosaBaix</NODE1_NAME>
          <NODE2_ID>1592</NODE2_ID>
          <NODE2_NAME>MallaSerrat</NODE2_NAME>
          <KMS>3.142</KMS>
          <LINK_TYPE>ap/client</LINK_TYPE>
          <STATUS>Working</STATUS>
          <ogr:geometryProperty><gml:LineString><gml:coordinates>2.260160,41.907340 2.233511,41.887250</gml:coordinates></gml:LineString></ogr:geometryProperty>
          </dlinks>
          </gml:featureMember>
          <gml:featureMember>
          <dlinks fid="17506">
          <NODE1_ID>16070</NODE1_ID>
          <NODE1_NAME>VicJMGomez</NODE1_NAME>
          <NODE2_ID>15036</NODE2_ID>
          <NODE2_NAME>VicSSantFerm</NODE2_NAME>
          <KMS>0.357</KMS>
          <LINK_TYPE>ap/client</LINK_TYPE>
          <STATUS>Working</STATUS>
          <ogr:geometryProperty><gml:LineString><gml:coordinates>2.258892,41.916577 2.256746,41.913791</gml:coordinates></gml:LineString></ogr:geometryProperty>
          </dlinks>
          </gml:featureMember>
          <gml:featureMember>
          <dlinks fid="17560">
          <NODE1_ID>22150</NODE1_ID>
          <NODE1_NAME>VICjfebrer</NODE1_NAME>
          <NODE2_ID>15036</NODE2_ID>
          <NODE2_NAME>VicSSantFerm</NODE2_NAME>
          <KMS>0.736</KMS>
          <LINK_TYPE>ap/client</LINK_TYPE>
          <STATUS>Working</STATUS>
          <ogr:geometryProperty><gml:LineString><gml:coordinates>2.257685,41.920380 2.256746,41.913791</gml:coordinates></gml:LineString></ogr:geometryProperty>
          </dlinks>
          </gml:featureMember>
          <gml:featureMember>
          <dlinks fid="17938">
          <NODE1_ID>9079</NODE1_ID>
          <NODE1_NAME>VicGarf</NODE1_NAME>
          <NODE2_ID>15035</NODE2_ID>
          <NODE2_NAME>VicPalauBojons</NODE2_NAME>
          <KMS>1.408</KMS>
          <LINK_TYPE>ap/client</LINK_TYPE>
          <STATUS>Working</STATUS>
          <ogr:geometryProperty><gml:LineString><gml:coordinates>2.260212,41.916628 2.257728,41.929168</gml:coordinates></gml:LineString></ogr:geometryProperty>
          </dlinks>
          </gml:featureMember>
          <gml:featureMember>
          <dlinks fid="18136">
          <NODE1_ID>22647</NODE1_ID>
          <NODE1_NAME>VicMontseSerra</NODE1_NAME>
          <NODE2_ID>15035</NODE2_ID>
          <NODE2_NAME>VicPalauBojons</NODE2_NAME>
          <KMS>0.604</KMS>
          <LINK_TYPE>ap/client</LINK_TYPE>
          <STATUS>Working</STATUS>
          <ogr:geometryProperty><gml:LineString><gml:coordinates>2.260770,41.924229 2.257728,41.929168</gml:coordinates></gml:LineString></ogr:geometryProperty>
          </dlinks>
          </gml:featureMember>
          <gml:featureMember>
          <dlinks fid="18911">
          <NODE1_ID>15036</NODE1_ID>
          <NODE1_NAME>VicSSantFerm</NODE1_NAME>
          <NODE2_ID>15263</NODE2_ID>
          <NODE2_NAME>VicSanfermAlbert</NODE2_NAME>
          <KMS>0.058</KMS>
          <LINK_TYPE>ap/client</LINK_TYPE>
          <STATUS>Working</STATUS>
          <ogr:geometryProperty><gml:LineString><gml:coordinates>2.256746,41.913791 2.256796,41.913274</gml:coordinates></gml:LineString></ogr:geometryProperty>
          </dlinks>
          </gml:featureMember>
          <gml:featureMember>
          <dlinks fid="19746">
          <NODE1_ID>24696</NODE1_ID>
          <NODE1_NAME>VicManuelUrena</NODE1_NAME>
          <NODE2_ID>21654</NODE2_ID>
          <NODE2_NAME>VicPsgGeneralitat55</NODE2_NAME>
          <KMS>0.547</KMS>
          <LINK_TYPE>ap/client</LINK_TYPE>
          <STATUS>Working</STATUS>
          <ogr:geometryProperty><gml:LineString><gml:coordinates>2.259112,41.919129 2.252608,41.919943</gml:coordinates></gml:LineString></ogr:geometryProperty>
          </dlinks>
          </gml:featureMember>
          <gml:featureMember>
          <dlinks fid="21675">
          <NODE1_ID>1711</NODE1_ID>
          <NODE1_NAME>VicHabitat</NODE1_NAME>
          <NODE2_ID>6580</NODE2_ID>
          <NODE2_NAME>VicBotanic</NODE2_NAME>
          <KMS>1.187</KMS>
          <LINK_TYPE>ap/client</LINK_TYPE>
          <STATUS>Working</STATUS>
          <ogr:geometryProperty><gml:LineString><gml:coordinates>2.249722,41.928333 2.257789,41.919501</gml:coordinates></gml:LineString></ogr:geometryProperty>
          </dlinks>
          </gml:featureMember>
          <gml:featureMember>
          <dlinks fid="22903">
          <NODE1_ID>28133</NODE1_ID>
          <NODE1_NAME>VicErra</NODE1_NAME>
          <NODE2_ID>15036</NODE2_ID>
          <NODE2_NAME>VicSSantFerm</NODE2_NAME>
          <KMS>0.047</KMS>
          <LINK_TYPE>ap/client</LINK_TYPE>
          <STATUS>Working</STATUS>
          <ogr:geometryProperty><gml:LineString><gml:coordinates>2.256907,41.913384 2.256746,41.913791</gml:coordinates></gml:LineString></ogr:geometryProperty>
          </dlinks>
          </gml:featureMember>
          <gml:featureMember>
          <dlinks fid="23643">
          <NODE1_ID>28833</NODE1_ID>
          <NODE1_NAME>VicEmiliStferm</NODE1_NAME>
          <NODE2_ID>15036</NODE2_ID>
          <NODE2_NAME>VicSSantFerm</NODE2_NAME>
          <KMS>0.094</KMS>
          <LINK_TYPE>ap/client</LINK_TYPE>
          <STATUS>Working</STATUS>
          <ogr:geometryProperty><gml:LineString><gml:coordinates>2.257492,41.913158 2.256746,41.913791</gml:coordinates></gml:LineString></ogr:geometryProperty>
          </dlinks>
          </gml:featureMember>
          <gml:featureMember>
          <dlinks fid="24007">
          <NODE1_ID>18572</NODE1_ID>
          <NODE1_NAME>VicManelJoan</NODE1_NAME>
          <NODE2_ID>18297</NODE2_ID>
          <NODE2_NAME>SEBCampFutbol</NODE2_NAME>
          <KMS>2.399</KMS>
          <LINK_TYPE>ap/client</LINK_TYPE>
          <STATUS>Working</STATUS>
          <ogr:geometryProperty><gml:LineString><gml:coordinates>2.260145,41.916671 2.278419,41.899936</gml:coordinates></gml:LineString></ogr:geometryProperty>
          </dlinks>
          </gml:featureMember>
          <gml:featureMember>
          <dlinks fid="24874">
          <NODE1_ID>29217</NODE1_ID>
          <NODE1_NAME>VicMaPra</NODE1_NAME>
          <NODE2_ID>15036</NODE2_ID>
          <NODE2_NAME>VicSSantFerm</NODE2_NAME>
          <KMS>0.435</KMS>
          <LINK_TYPE>ap/client</LINK_TYPE>
          <STATUS>Working</STATUS>
          <ogr:geometryProperty><gml:LineString><gml:coordinates>2.256588,41.917705 2.256746,41.913791</gml:coordinates></gml:LineString></ogr:geometryProperty>
          </dlinks>
          </gml:featureMember>
          <gml:featureMember>
          <dlinks fid="24997">
          <NODE1_ID>30271</NODE1_ID>
          <NODE1_NAME>VicMohamedSF</NODE1_NAME>
          <NODE2_ID>21654</NODE2_ID>
          <NODE2_NAME>VicPsgGeneralitat55</NODE2_NAME>
          <KMS>0.677</KMS>
          <LINK_TYPE>ap/client</LINK_TYPE>
          <STATUS>Working</STATUS>
          <ogr:geometryProperty><gml:LineString><gml:coordinates>2.259214,41.916366 2.252608,41.919943</gml:coordinates></gml:LineString></ogr:geometryProperty>
          </dlinks>
          </gml:featureMember>
          <gml:featureMember>
          <dlinks fid="25246">
          <NODE1_ID>15036</NODE1_ID>
          <NODE1_NAME>VicSSantFerm</NODE1_NAME>
          <NODE2_ID>30524</NODE2_ID>
          <NODE2_NAME>VicStfermfrancesc</NODE2_NAME>
          <KMS>0.124</KMS>
          <LINK_TYPE>ap/client</LINK_TYPE>
          <STATUS>Working</STATUS>
          <ogr:geometryProperty><gml:LineString><gml:coordinates>2.256746,41.913791 2.256934,41.912681</gml:coordinates></gml:LineString></ogr:geometryProperty>
          </dlinks>
          </gml:featureMember>
          <gml:featureMember>
          <dlinks fid="26173">
          <NODE1_ID>31576</NODE1_ID>
          <NODE1_NAME>Vicerra-2</NODE1_NAME>
          <NODE2_ID>6776</NODE2_ID>
          <NODE2_NAME>CallSerrat</NODE2_NAME>
          <KMS>2.356</KMS>
          <LINK_TYPE>ap/client</LINK_TYPE>
          <STATUS>Working</STATUS>
          <ogr:geometryProperty><gml:LineString><gml:coordinates>2.256982,41.913404 2.282194,41.923173</gml:coordinates></gml:LineString></ogr:geometryProperty>
          </dlinks>
          </gml:featureMember>
          <gml:featureMember>
          <dlinks fid="29390">
          <NODE1_ID>14765</NODE1_ID>
          <NODE1_NAME>VicCarlesG</NODE1_NAME>
          <NODE2_ID>15036</NODE2_ID>
          <NODE2_NAME>VicSSantFerm</NODE2_NAME>
          <KMS>0.297</KMS>
          <LINK_TYPE>ap/client</LINK_TYPE>
          <STATUS>Working</STATUS>
          <ogr:geometryProperty><gml:LineString><gml:coordinates>2.258967,41.915883 2.256746,41.913791</gml:coordinates></gml:LineString></ogr:geometryProperty>
          </dlinks>
          </gml:featureMember>
          <gml:featureMember>
          <dlinks fid="30406">
          <NODE1_ID>35564</NODE1_ID>
          <NODE1_NAME>VicCapdevila</NODE1_NAME>
          <NODE2_ID>15036</NODE2_ID>
          <NODE2_NAME>VicSSantFerm</NODE2_NAME>
          <KMS>0.104</KMS>
          <LINK_TYPE>ap/client</LINK_TYPE>
          <STATUS>Working</STATUS>
          <ogr:geometryProperty><gml:LineString><gml:coordinates>2.257673,41.913165 2.256746,41.913791</gml:coordinates></gml:LineString></ogr:geometryProperty>
          </dlinks>
          </gml:featureMember>
          <gml:featureMember>
          <dlinks fid="31479">
          <NODE1_ID>36328</NODE1_ID>
          <NODE1_NAME>VicJoanMir</NODE1_NAME>
          <NODE2_ID>18297</NODE2_ID>
          <NODE2_NAME>SEBCampFutbol</NODE2_NAME>
          <KMS>2.209</KMS>
          <LINK_TYPE>ap/client</LINK_TYPE>
          <STATUS>Working</STATUS>
          <ogr:geometryProperty><gml:LineString><gml:coordinates>2.260394,41.914573 2.278419,41.899936</gml:coordinates></gml:LineString></ogr:geometryProperty>
          </dlinks>
          </gml:featureMember>
          <gml:featureMember>
          <dlinks fid="31517">
          <NODE1_ID>36327</NODE1_ID>
          <NODE1_NAME>VicJutgla</NODE1_NAME>
          <NODE2_ID>18297</NODE2_ID>
          <NODE2_NAME>SEBCampFutbol</NODE2_NAME>
          <KMS>2.186</KMS>
          <LINK_TYPE>ap/client</LINK_TYPE>
          <STATUS>Working</STATUS>
          <ogr:geometryProperty><gml:LineString><gml:coordinates>2.260536,41.914384 2.278419,41.899936</gml:coordinates></gml:LineString></ogr:geometryProperty>
          </dlinks>
          </gml:featureMember>
          <gml:featureMember>
          <dlinks fid="39883">
          <NODE1_ID>43556</NODE1_ID>
          <NODE1_NAME>VicRomaBC</NODE1_NAME>
          <NODE2_ID>1711</NODE2_ID>
          <NODE2_NAME>VicHabitat</NODE2_NAME>
          <KMS>1.554</KMS>
          <LINK_TYPE>ap/client</LINK_TYPE>
          <STATUS>Working</STATUS>
          <ogr:geometryProperty><gml:LineString><gml:coordinates>2.260075,41.916671 2.249722,41.928333</gml:coordinates></gml:LineString></ogr:geometryProperty>
          </dlinks>
          </gml:featureMember>
          <gml:featureMember>
          <dlinks fid="43574">
          <NODE1_ID>15189</NODE1_ID>
          <NODE1_NAME>VicJAltarriba</NODE1_NAME>
          <NODE2_ID>1711</NODE2_ID>
          <NODE2_NAME>VicHabitat</NODE2_NAME>
          <KMS>1.535</KMS>
          <LINK_TYPE>ap/client</LINK_TYPE>
          <STATUS>Working</STATUS>
          <ogr:geometryProperty><gml:LineString><gml:coordinates>2.258798,41.916292 2.249722,41.928333</gml:coordinates></gml:LineString></ogr:geometryProperty>
          </dlinks>
          </gml:featureMember>
          <gml:featureMember>
          <dlinks fid="44550">
          <NODE1_ID>47062</NODE1_ID>
          <NODE1_NAME>VicOmniumSonia</NODE1_NAME>
          <NODE2_ID>15036</NODE2_ID>
          <NODE2_NAME>VicSSantFerm</NODE2_NAME>
          <KMS>0.348</KMS>
          <LINK_TYPE>ap/client</LINK_TYPE>
          <STATUS>Working</STATUS>
          <ogr:geometryProperty><gml:LineString><gml:coordinates>2.258616,41.916594 2.256746,41.913791</gml:coordinates></gml:LineString></ogr:geometryProperty>
          </dlinks>
          </gml:featureMember>
          <gml:featureMember>
          <dlinks fid="44621">
          <NODE1_ID>36738</NODE1_ID>
          <NODE1_NAME>VicPlacaosona9</NODE1_NAME>
          <NODE2_ID>40034</NODE2_ID>
          <NODE2_NAME>VicSubVigatana</NODE2_NAME>
          <KMS>0.481</KMS>
          <LINK_TYPE>ap/client</LINK_TYPE>
          <STATUS>Working</STATUS>
          <ogr:geometryProperty><gml:LineString><gml:coordinates>2.259670,41.915781 2.258769,41.920062</gml:coordinates></gml:LineString></ogr:geometryProperty>
          </dlinks>
          </gml:featureMember>
          <gml:featureMember>
          <dlinks fid="45132">
          <NODE1_ID>19709</NODE1_ID>
          <NODE1_NAME>VicGomez</NODE1_NAME>
          <NODE2_ID>40034</NODE2_ID>
          <NODE2_NAME>VicSubVigatana</NODE2_NAME>
          <KMS>0.173</KMS>
          <LINK_TYPE>ap/client</LINK_TYPE>
          <STATUS>Working</STATUS>
          <ogr:geometryProperty><gml:LineString><gml:coordinates>2.257495,41.918830 2.258769,41.920062</gml:coordinates></gml:LineString></ogr:geometryProperty>
          </dlinks>
          </gml:featureMember>
          <gml:featureMember>
          <dlinks fid="47821">
          <NODE1_ID>35496</NODE1_ID>
          <NODE1_NAME>VicMariaEngracia</NODE1_NAME>
          <NODE2_ID>7859</NODE2_ID>
          <NODE2_NAME>GXACampanar</NODE2_NAME>
          <KMS>2.347</KMS>
          <LINK_TYPE>ap/client</LINK_TYPE>
          <STATUS>Planned</STATUS>
          <ogr:geometryProperty><gml:LineString><gml:coordinates>2.256250,41.913626 2.227957,41.913525</gml:coordinates></gml:LineString></ogr:geometryProperty>
          </dlinks>
          </gml:featureMember>
          <gml:featureMember>
          <dlinks fid="48034">
          <NODE1_ID>49837</NODE1_ID>
          <NODE1_NAME>VicJaki2</NODE1_NAME>
          <NODE2_ID>40034</NODE2_ID>
          <NODE2_NAME>VicSubVigatana</NODE2_NAME>
          <KMS>0.487</KMS>
          <LINK_TYPE>ap/client</LINK_TYPE>
          <STATUS>Working</STATUS>
          <ogr:geometryProperty><gml:LineString><gml:coordinates>2.252907,41.920242 2.258769,41.920062</gml:coordinates></gml:LineString></ogr:geometryProperty>
          </dlinks>
          </gml:featureMember>
          <gml:featureMember>
          <dlinks fid="48554">
          <NODE1_ID>40034</NODE1_ID>
          <NODE1_NAME>VicSubVigatana</NODE1_NAME>
          <NODE2_ID>14736</NODE2_ID>
          <NODE2_NAME>VicMohamedC</NODE2_NAME>
          <KMS>0.854</KMS>
          <LINK_TYPE>ap/client</LINK_TYPE>
          <STATUS>Working</STATUS>
          <ogr:geometryProperty><gml:LineString><gml:coordinates>2.258769,41.920062 2.255675,41.912728</gml:coordinates></gml:LineString></ogr:geometryProperty>
          </dlinks>
          </gml:featureMember>
          <gml:featureMember>
          <dlinks fid="51072">
          <NODE1_ID>52117</NODE1_ID>
          <NODE1_NAME>VicMMartinez</NODE1_NAME>
          <NODE2_ID>40034</NODE2_ID>
          <NODE2_NAME>VicSubVigatana</NODE2_NAME>
          <KMS>0.383</KMS>
          <LINK_TYPE>ap/client</LINK_TYPE>
          <STATUS>Working</STATUS>
          <ogr:geometryProperty><gml:LineString><gml:coordinates>2.259589,41.916670 2.258769,41.920062</gml:coordinates></gml:LineString></ogr:geometryProperty>
          </dlinks>
          </gml:featureMember>
          <gml:featureMember>
          <dlinks fid="51611">
          <NODE1_ID>40034</NODE1_ID>
          <NODE1_NAME>VicSubVigatana</NODE1_NAME>
          <NODE2_ID>45750</NODE2_ID>
          <NODE2_NAME>VicOmnium844</NODE2_NAME>
          <KMS>0.397</KMS>
          <LINK_TYPE>ap/client</LINK_TYPE>
          <STATUS>Working</STATUS>
          <ogr:geometryProperty><gml:LineString><gml:coordinates>2.258769,41.920062 2.259533,41.916533</gml:coordinates></gml:LineString></ogr:geometryProperty>
          </dlinks>
          </gml:featureMember>
          <gml:featureMember>
          <dlinks fid="51615">
          <NODE1_ID>8447</NODE1_ID>
          <NODE1_NAME>VicRPuges</NODE1_NAME>
          <NODE2_ID>40034</NODE2_ID>
          <NODE2_NAME>VicSubVigatana</NODE2_NAME>
          <KMS>0.219</KMS>
          <LINK_TYPE>ap/client</LINK_TYPE>
          <STATUS>Working</STATUS>
          <ogr:geometryProperty><gml:LineString><gml:coordinates>2.256853,41.918708 2.258769,41.920062</gml:coordinates></gml:LineString></ogr:geometryProperty>
          </dlinks>
          </gml:featureMember>
          <gml:featureMember>
          <dlinks fid="52049">
          <NODE1_ID>2905</NODE1_ID>
          <NODE1_NAME>VicBotanicMico34</NODE1_NAME>
          <NODE2_ID>40034</NODE2_ID>
          <NODE2_NAME>VicSubVigatana</NODE2_NAME>
          <KMS>0.241</KMS>
          <LINK_TYPE>ap/client</LINK_TYPE>
          <STATUS>Working</STATUS>
          <ogr:geometryProperty><gml:LineString><gml:coordinates>2.257866,41.918003 2.258769,41.920062</gml:coordinates></gml:LineString></ogr:geometryProperty>
          </dlinks>
          </gml:featureMember>
          <gml:featureMember>
          <dlinks fid="52466">
          <NODE1_ID>16650</NODE1_ID>
          <NODE1_NAME>VicPgDrRobert21</NODE1_NAME>
          <NODE2_ID>40034</NODE2_ID>
          <NODE2_NAME>VicSubVigatana</NODE2_NAME>
          <KMS>0.216</KMS>
          <LINK_TYPE>ap/client</LINK_TYPE>
          <STATUS>Working</STATUS>
          <ogr:geometryProperty><gml:LineString><gml:coordinates>2.256971,41.918654 2.258769,41.920062</gml:coordinates></gml:LineString></ogr:geometryProperty>
          </dlinks>
          </gml:featureMember>
          <gml:featureMember>
          <dlinks fid="52856">
          <NODE1_ID>53357</NODE1_ID>
          <NODE1_NAME>VicStJaume84</NODE1_NAME>
          <NODE2_ID>40034</NODE2_ID>
          <NODE2_NAME>VicSubVigatana</NODE2_NAME>
          <KMS>0.138</KMS>
          <LINK_TYPE>ap/client</LINK_TYPE>
          <STATUS>Working</STATUS>
          <ogr:geometryProperty><gml:LineString><gml:coordinates>2.259262,41.918878 2.258769,41.920062</gml:coordinates></gml:LineString></ogr:geometryProperty>
          </dlinks>
          </gml:featureMember>
          <gml:featureMember>
          <dlinks fid="52860">
          <NODE1_ID>53361</NODE1_ID>
          <NODE1_NAME>Vicosona7</NODE1_NAME>
          <NODE2_ID>40034</NODE2_ID>
          <NODE2_NAME>VicSubVigatana</NODE2_NAME>
          <KMS>0.518</KMS>
          <LINK_TYPE>ap/client</LINK_TYPE>
          <STATUS>Working</STATUS>
          <ogr:geometryProperty><gml:LineString><gml:coordinates>2.259545,41.915439 2.258769,41.920062</gml:coordinates></gml:LineString></ogr:geometryProperty>
          </dlinks>
          </gml:featureMember>
          <gml:featureMember>
          <dlinks fid="53300">
          <NODE1_ID>42819</NODE1_ID>
          <NODE1_NAME>VicMontseR</NODE1_NAME>
          <NODE2_ID>1711</NODE2_ID>
          <NODE2_NAME>VicHabitat</NODE2_NAME>
          <KMS>1.827</KMS>
          <LINK_TYPE>ap/client</LINK_TYPE>
          <STATUS>Working</STATUS>
          <ogr:geometryProperty><gml:LineString><gml:coordinates>2.256789,41.912752 2.249722,41.928333</gml:coordinates></gml:LineString></ogr:geometryProperty>
          </dlinks>
          </gml:featureMember>
          <gml:featureMember>
          <dlinks fid="53301">
          <NODE1_ID>42819</NODE1_ID>
          <NODE1_NAME>VicMontseR</NODE1_NAME>
          <NODE2_ID>2231</NODE2_ID>
          <NODE2_NAME>TonaCastell</NODE2_NAME>
          <KMS>7.061</KMS>
          <LINK_TYPE>ap/client</LINK_TYPE>
          <STATUS>Planned</STATUS>
          <ogr:geometryProperty><gml:LineString><gml:coordinates>2.256789,41.912752 2.224624,41.853904</gml:coordinates></gml:LineString></ogr:geometryProperty>
          </dlinks>
          </gml:featureMember>
          <gml:featureMember>
          <dlinks fid="53406">
          <NODE1_ID>15036</NODE1_ID>
          <NODE1_NAME>VicSSantFerm</NODE1_NAME>
          <NODE2_ID>1592</NODE2_ID>
          <NODE2_NAME>MallaSerrat</NODE2_NAME>
          <KMS>3.522</KMS>
          <LINK_TYPE>ap/client</LINK_TYPE>
          <STATUS>Planned</STATUS>
          <ogr:geometryProperty><gml:LineString><gml:coordinates>2.256746,41.913791 2.233511,41.887250</gml:coordinates></gml:LineString></ogr:geometryProperty>
          </dlinks>
          </gml:featureMember>
          <gml:featureMember>
          <dlinks fid="53621">
          <NODE1_ID>53947</NODE1_ID>
          <NODE1_NAME>VicBodoy</NODE1_NAME>
          <NODE2_ID>40034</NODE2_ID>
          <NODE2_NAME>VicSubVigatana</NODE2_NAME>
          <KMS>0.257</KMS>
          <LINK_TYPE>ap/client</LINK_TYPE>
          <STATUS>Working</STATUS>
          <ogr:geometryProperty><gml:LineString><gml:coordinates>2.256956,41.918190 2.258769,41.920062</gml:coordinates></gml:LineString></ogr:geometryProperty>
          </dlinks>
          </gml:featureMember>
          <gml:featureMember>
          <dlinks fid="54330">
          <NODE1_ID>54186</NODE1_ID>
          <NODE1_NAME>VicMMola</NODE1_NAME>
          <NODE2_ID>1711</NODE2_ID>
          <NODE2_NAME>VicHabitat</NODE2_NAME>
          <KMS>0.716</KMS>
          <LINK_TYPE>ap/client</LINK_TYPE>
          <STATUS>Working</STATUS>
          <ogr:geometryProperty><gml:LineString><gml:coordinates>2.250765,41.921938 2.249722,41.928333</gml:coordinates></gml:LineString></ogr:geometryProperty>
          </dlinks>
          </gml:featureMember>
          <gml:featureMember>
          <dlinks fid="55309">
          <NODE1_ID>44078</NODE1_ID>
          <NODE1_NAME>VicKoulij</NODE1_NAME>
          <NODE2_ID>40034</NODE2_ID>
          <NODE2_NAME>VicSubVigatana</NODE2_NAME>
          <KMS>0.864</KMS>
          <LINK_TYPE>ap/client</LINK_TYPE>
          <STATUS>Working</STATUS>
          <ogr:geometryProperty><gml:LineString><gml:coordinates>2.255373,41.912709 2.258769,41.920062</gml:coordinates></gml:LineString></ogr:geometryProperty>
          </dlinks>
          </gml:featureMember>
          <gml:featureMember>
          <dlinks fid="55424">
          <NODE1_ID>31534</NODE1_ID>
          <NODE1_NAME>VicIvan</NODE1_NAME>
          <NODE2_ID>40034</NODE2_ID>
          <NODE2_NAME>VicSubVigatana</NODE2_NAME>
          <KMS>0.828</KMS>
          <LINK_TYPE>ap/client</LINK_TYPE>
          <STATUS>Working</STATUS>
          <ogr:geometryProperty><gml:LineString><gml:coordinates>2.255314,41.913064 2.258769,41.920062</gml:coordinates></gml:LineString></ogr:geometryProperty>
          </dlinks>
          </gml:featureMember>
          <gml:featureMember>
          <dlinks fid="57354">
          <NODE1_ID>1711</NODE1_ID>
          <NODE1_NAME>VicHabitat</NODE1_NAME>
          <NODE2_ID>56557</NODE2_ID>
          <NODE2_NAME>VicYou4</NODE2_NAME>
          <KMS>1.568</KMS>
          <LINK_TYPE>ap/client</LINK_TYPE>
          <STATUS>Working</STATUS>
          <ogr:geometryProperty><gml:LineString><gml:coordinates>2.249722,41.928333 2.260029,41.916498</gml:coordinates></gml:LineString></ogr:geometryProperty>
          </dlinks>
          </gml:featureMember>
          <gml:featureMember>
          <dlinks fid="57987">
          <NODE1_ID>54779</NODE1_ID>
          <NODE1_NAME>VicEduardIllamola</NODE1_NAME>
          <NODE2_ID>1592</NODE2_ID>
          <NODE2_NAME>MallaSerrat</NODE2_NAME>
          <KMS>3.556</KMS>
          <LINK_TYPE>ap/client</LINK_TYPE>
          <STATUS>Working</STATUS>
          <ogr:geometryProperty><gml:LineString><gml:coordinates>2.260849,41.911910 2.233511,41.887250</gml:coordinates></gml:LineString></ogr:geometryProperty>
          </dlinks>
          </gml:featureMember>
          <gml:featureMember>
          <dlinks fid="60637">
          <NODE1_ID>56540</NODE1_ID>
          <NODE1_NAME>VicCarrerPi</NODE1_NAME>
          <NODE2_ID>15036</NODE2_ID>
          <NODE2_NAME>VicSSantFerm</NODE2_NAME>
          <KMS>0.194</KMS>
          <LINK_TYPE>ap/client</LINK_TYPE>
          <STATUS>Working</STATUS>
          <ogr:geometryProperty><gml:LineString><gml:coordinates>2.255096,41.912556 2.256746,41.913791</gml:coordinates></gml:LineString></ogr:geometryProperty>
          </dlinks>
          </gml:featureMember>
          <gml:featureMember>
          <dlinks fid="64204">
          <NODE1_ID>57929</NODE1_ID>
          <NODE1_NAME>VicRamonLlull24</NODE1_NAME>
          <NODE2_ID>6776</NODE2_ID>
          <NODE2_NAME>CallSerrat</NODE2_NAME>
          <KMS>2.01</KMS>
          <LINK_TYPE>ap/client</LINK_TYPE>
          <STATUS>Working</STATUS>
          <ogr:geometryProperty><gml:LineString><gml:coordinates>2.258793,41.918485 2.282194,41.923173</gml:coordinates></gml:LineString></ogr:geometryProperty>
          </dlinks>
          </gml:featureMember>
          <gml:featureMember>
          <dlinks fid="64404">
          <NODE1_ID>1641</NODE1_ID>
          <NODE1_NAME>VicPlacaEloi</NODE1_NAME>
          <NODE2_ID>15036</NODE2_ID>
          <NODE2_NAME>VicSSantFerm</NODE2_NAME>
          <KMS>1.841</KMS>
          <LINK_TYPE>wds</LINK_TYPE>
          <STATUS>Working</STATUS>
          <ogr:geometryProperty><gml:LineString><gml:coordinates>2.255099,41.930320 2.256746,41.913791</gml:coordinates></gml:LineString></ogr:geometryProperty>
          </dlinks>
          </gml:featureMember>
          <gml:featureMember>
          <dlinks fid="64480">
          <NODE1_ID>61656</NODE1_ID>
          <NODE1_NAME>VicBouzian</NODE1_NAME>
          <NODE2_ID>34012</NODE2_ID>
          <NODE2_NAME>VicPietat</NODE2_NAME>
          <KMS>0.671</KMS>
          <LINK_TYPE>ap/client</LINK_TYPE>
          <STATUS>Working</STATUS>
          <ogr:geometryProperty><gml:LineString><gml:coordinates>2.256532,41.923256 2.256462,41.929300</gml:coordinates></gml:LineString></ogr:geometryProperty>
          </dlinks>
          </gml:featureMember>
          <gml:featureMember>
          <dlinks fid="65245">
          <NODE1_ID>16011</NODE1_ID>
          <NODE1_NAME>VicECasademunt</NODE1_NAME>
          <NODE2_ID>11770</NODE2_ID>
          <NODE2_NAME>VicRavalCortinesST</NODE2_NAME>
          <KMS>1.757</KMS>
          <LINK_TYPE>ap/client</LINK_TYPE>
          <STATUS>Working</STATUS>
          <ogr:geometryProperty><gml:LineString><gml:coordinates>2.260285,41.914990 2.262277,41.930738</gml:coordinates></gml:LineString></ogr:geometryProperty>
          </dlinks>
          </gml:featureMember>
          <gml:featureMember>
          <dlinks fid="65286">
          <NODE1_ID>62306</NODE1_ID>
          <NODE1_NAME>VicGerard</NODE1_NAME>
          <NODE2_ID>40034</NODE2_ID>
          <NODE2_NAME>VicSubVigatana</NODE2_NAME>
          <KMS>0.752</KMS>
          <LINK_TYPE>ap/client</LINK_TYPE>
          <STATUS>Working</STATUS>
          <ogr:geometryProperty><gml:LineString><gml:coordinates>2.257977,41.913322 2.258769,41.920062</gml:coordinates></gml:LineString></ogr:geometryProperty>
          </dlinks>
          </gml:featureMember>
          <gml:featureMember>
          <dlinks fid="65394">
          <NODE1_ID>62417</NODE1_ID>
          <NODE1_NAME>VicMMolist</NODE1_NAME>
          <NODE2_ID>11770</NODE2_ID>
          <NODE2_NAME>VicRavalCortinesST</NODE2_NAME>
          <KMS>0.957</KMS>
          <LINK_TYPE>ap/client</LINK_TYPE>
          <STATUS>Working</STATUS>
          <ogr:geometryProperty><gml:LineString><gml:coordinates>2.269878,41.924261 2.262277,41.930738</gml:coordinates></gml:LineString></ogr:geometryProperty>
          </dlinks>
          </gml:featureMember>
          <gml:featureMember>
          <dlinks fid="65761">
          <NODE1_ID>38616</NODE1_ID>
          <NODE1_NAME>VicJDomenech</NODE1_NAME>
          <NODE2_ID>21654</NODE2_ID>
          <NODE2_NAME>VicPsgGeneralitat55</NODE2_NAME>
          <KMS>0.175</KMS>
          <LINK_TYPE>ap/client</LINK_TYPE>
          <STATUS>Working</STATUS>
          <ogr:geometryProperty><gml:LineString><gml:coordinates>2.254716,41.919990 2.252608,41.919943</gml:coordinates></gml:LineString></ogr:geometryProperty>
          </dlinks>
          </gml:featureMember>
          <gml:featureMember>
          <dlinks fid="65797">
          <NODE1_ID>23352</NODE1_ID>
          <NODE1_NAME>VicTorreDEnFranc</NODE1_NAME>
          <NODE2_ID>21654</NODE2_ID>
          <NODE2_NAME>VicPsgGeneralitat55</NODE2_NAME>
          <KMS>0.347</KMS>
          <LINK_TYPE>ap/client</LINK_TYPE>
          <STATUS>Working</STATUS>
          <ogr:geometryProperty><gml:LineString><gml:coordinates>2.252456,41.916825 2.252608,41.919943</gml:coordinates></gml:LineString></ogr:geometryProperty>
          </dlinks>
          </gml:featureMember>
          <gml:featureMember>
          <dlinks fid="67268">
          <NODE1_ID>23316</NODE1_ID>
          <NODE1_NAME>VicSamir</NODE1_NAME>
          <NODE2_ID>21654</NODE2_ID>
          <NODE2_NAME>VicPsgGeneralitat55</NODE2_NAME>
          <KMS>0.907</KMS>
          <LINK_TYPE>ap/client</LINK_TYPE>
          <STATUS>Working</STATUS>
          <ogr:geometryProperty><gml:LineString><gml:coordinates>2.257744,41.912737 2.252608,41.919943</gml:coordinates></gml:LineString></ogr:geometryProperty>
          </dlinks>
          </gml:featureMember>
          <gml:featureMember>
          <dlinks fid="68115">
          <NODE1_ID>63593</NODE1_ID>
          <NODE1_NAME>VicASalesa</NODE1_NAME>
          <NODE2_ID>21654</NODE2_ID>
          <NODE2_NAME>VicPsgGeneralitat55</NODE2_NAME>
          <KMS>0.693</KMS>
          <LINK_TYPE>ap/client</LINK_TYPE>
          <STATUS>Working</STATUS>
          <ogr:geometryProperty><gml:LineString><gml:coordinates>2.259662,41.916609 2.252608,41.919943</gml:coordinates></gml:LineString></ogr:geometryProperty>
          </dlinks>
          </gml:featureMember>
          <gml:featureMember>
          <dlinks fid="68517">
          <NODE1_ID>21654</NODE1_ID>
          <NODE1_NAME>VicPsgGeneralitat55</NODE1_NAME>
          <NODE2_ID>15036</NODE2_ID>
          <NODE2_NAME>VicSSantFerm</NODE2_NAME>
          <KMS>0.765</KMS>
          <LINK_TYPE>wds</LINK_TYPE>
          <STATUS>Working</STATUS>
          <ogr:geometryProperty><gml:LineString><gml:coordinates>2.252608,41.919943 2.256746,41.913791</gml:coordinates></gml:LineString></ogr:geometryProperty>
          </dlinks>
          </gml:featureMember>
          <gml:featureMember>
          <dlinks fid="68571">
          <NODE1_ID>64146</NODE1_ID>
          <NODE1_NAME>VicIMesaoudi</NODE1_NAME>
          <NODE2_ID>21654</NODE2_ID>
          <NODE2_NAME>VicPsgGeneralitat55</NODE2_NAME>
          <KMS>0.685</KMS>
          <LINK_TYPE>ap/client</LINK_TYPE>
          <STATUS>Working</STATUS>
          <ogr:geometryProperty><gml:LineString><gml:coordinates>2.258667,41.915759 2.252608,41.919943</gml:coordinates></gml:LineString></ogr:geometryProperty>
          </dlinks>
          </gml:featureMember>
          <gml:featureMember>
          <dlinks fid="68985">
          <NODE1_ID>62485</NODE1_ID>
          <NODE1_NAME>VicJaumeP</NODE1_NAME>
          <NODE2_ID>3285</NODE2_ID>
          <NODE2_NAME>SEBAjuntament</NODE2_NAME>
          <KMS>2.527</KMS>
          <LINK_TYPE>ap/client</LINK_TYPE>
          <STATUS>Working</STATUS>
          <ogr:geometryProperty><gml:LineString><gml:coordinates>2.259420,41.914735 2.282921,41.900266</gml:coordinates></gml:LineString></ogr:geometryProperty>
          </dlinks>
          </gml:featureMember>
          <gml:featureMember>
          <dlinks fid="69917">
          <NODE1_ID>40034</NODE1_ID>
          <NODE1_NAME>VicSubVigatana</NODE1_NAME>
          <NODE2_ID>60485</NODE2_ID>
          <NODE2_NAME>VicDavidO</NODE2_NAME>
          <KMS>0.385</KMS>
          <LINK_TYPE>ap/client</LINK_TYPE>
          <STATUS>Working</STATUS>
          <ogr:geometryProperty><gml:LineString><gml:coordinates>2.258769,41.920062 2.259074,41.916607</gml:coordinates></gml:LineString></ogr:geometryProperty>
          </dlinks>
          </gml:featureMember>
          <gml:featureMember>
          <dlinks fid="70259">
          <NODE1_ID>65968</NODE1_ID>
          <NODE1_NAME>VicBotMico103</NODE1_NAME>
          <NODE2_ID>21654</NODE2_ID>
          <NODE2_NAME>VicPsgGeneralitat55</NODE2_NAME>
          <KMS>0.752</KMS>
          <LINK_TYPE>ap/client</LINK_TYPE>
          <STATUS>Working</STATUS>
          <ogr:geometryProperty><gml:LineString><gml:coordinates>2.258769,41.914982 2.252608,41.919943</gml:coordinates></gml:LineString></ogr:geometryProperty>
          </dlinks>
          </gml:featureMember>
          <gml:featureMember>
          <dlinks fid="72624">
          <NODE1_ID>49776</NODE1_ID>
          <NODE1_NAME>VicJacme</NODE1_NAME>
          <NODE2_ID>28311</NODE2_ID>
          <NODE2_NAME>VicVIT</NODE2_NAME>
          <KMS>0.6</KMS>
          <LINK_TYPE>ap/client</LINK_TYPE>
          <STATUS>Working</STATUS>
          <ogr:geometryProperty><gml:LineString><gml:coordinates>2.251625,41.921351 2.247916,41.925993</gml:coordinates></gml:LineString></ogr:geometryProperty>
          </dlinks>
          </gml:featureMember>
          <gml:featureMember>
          <dlinks fid="72652">
          <NODE1_ID>11770</NODE1_ID>
          <NODE1_NAME>VicRavalCortinesST</NODE1_NAME>
          <NODE2_ID>30497</NODE2_ID>
          <NODE2_NAME>VicFemi</NODE2_NAME>
          <KMS>0.382</KMS>
          <LINK_TYPE>ap/client</LINK_TYPE>
          <STATUS>Working</STATUS>
          <ogr:geometryProperty><gml:LineString><gml:coordinates>2.262277,41.930738 2.265067,41.928002</gml:coordinates></gml:LineString></ogr:geometryProperty>
          </dlinks>
          </gml:featureMember>
          <gml:featureMember>
          <dlinks fid="72903">
          <NODE1_ID>1711</NODE1_ID>
          <NODE1_NAME>VicHabitat</NODE1_NAME>
          <NODE2_ID>52413</NODE2_ID>
          <NODE2_NAME>VicOmniumHome</NODE2_NAME>
          <KMS>1.513</KMS>
          <LINK_TYPE>ap/client</LINK_TYPE>
          <STATUS>Planned</STATUS>
          <ogr:geometryProperty><gml:LineString><gml:coordinates>2.249722,41.928333 2.258488,41.916389</gml:coordinates></gml:LineString></ogr:geometryProperty>
          </dlinks>
          </gml:featureMember>
          <gml:featureMember>
          <dlinks fid="73503">
          <NODE1_ID>68816</NODE1_ID>
          <NODE1_NAME>VicMSibina</NODE1_NAME>
          <NODE2_ID>21654</NODE2_ID>
          <NODE2_NAME>VicPsgGeneralitat55</NODE2_NAME>
          <KMS>0.316</KMS>
          <LINK_TYPE>ap/client</LINK_TYPE>
          <STATUS>Working</STATUS>
          <ogr:geometryProperty><gml:LineString><gml:coordinates>2.256108,41.918811 2.252608,41.919943</gml:coordinates></gml:LineString></ogr:geometryProperty>
          </dlinks>
          </gml:featureMember>
          <gml:featureMember>
          <dlinks fid="75594">
          <NODE1_ID>20817</NODE1_ID>
          <NODE1_NAME>VicFrares34</NODE1_NAME>
          <NODE2_ID>3285</NODE2_ID>
          <NODE2_NAME>SEBAjuntament</NODE2_NAME>
          <KMS>2.449</KMS>
          <LINK_TYPE>ap/client</LINK_TYPE>
          <STATUS>Working</STATUS>
          <ogr:geometryProperty><gml:LineString><gml:coordinates>2.260352,41.914477 2.282921,41.900266</gml:coordinates></gml:LineString></ogr:geometryProperty>
          </dlinks>
          </gml:featureMember>
          <gml:featureMember>
          <dlinks fid="77697">
          <NODE1_ID>30958</NODE1_ID>
          <NODE1_NAME>VicEmili_f</NODE1_NAME>
          <NODE2_ID>40034</NODE2_ID>
          <NODE2_NAME>VicSubVigatana</NODE2_NAME>
          <KMS>0.232</KMS>
          <LINK_TYPE>ap/client</LINK_TYPE>
          <STATUS>Working</STATUS>
          <ogr:geometryProperty><gml:LineString><gml:coordinates>2.258120,41.918031 2.258769,41.920062</gml:coordinates></gml:LineString></ogr:geometryProperty>
          </dlinks>
          </gml:featureMember>
          <gml:featureMember>
          <dlinks fid="78367">
          <NODE1_ID>5307</NODE1_ID>
          <NODE1_NAME>VicBeth</NODE1_NAME>
          <NODE2_ID>40034</NODE2_ID>
          <NODE2_NAME>VicSubVigatana</NODE2_NAME>
          <KMS>0.778</KMS>
          <LINK_TYPE>ap/client</LINK_TYPE>
          <STATUS>Working</STATUS>
          <ogr:geometryProperty><gml:LineString><gml:coordinates>2.258405,41.913063 2.258769,41.920062</gml:coordinates></gml:LineString></ogr:geometryProperty>
          </dlinks>
          </gml:featureMember>
          <gml:featureMember>
          <dlinks fid="121623">
          <NODE1_ID>47814</NODE1_ID>
          <NODE1_NAME>VicJaki</NODE1_NAME>
          <NODE2_ID>40034</NODE2_ID>
          <NODE2_NAME>VicSubVigatana</NODE2_NAME>
          <KMS>0.506</KMS>
          <LINK_TYPE>ap/client</LINK_TYPE>
          <STATUS>Working</STATUS>
          <ogr:geometryProperty><gml:LineString><gml:coordinates>2.252683,41.920303 2.258769,41.920062</gml:coordinates></gml:LineString></ogr:geometryProperty>
          </dlinks>
          </gml:featureMember>
          <gml:featureMember>
          <dlinks fid="122903">
          <NODE1_ID>15299</NODE1_ID>
          <NODE1_NAME>VicCCarreno</NODE1_NAME>
          <NODE2_ID>1711</NODE2_ID>
          <NODE2_NAME>VicHabitat</NODE2_NAME>
          <KMS>1.54</KMS>
          <LINK_TYPE>ap/client</LINK_TYPE>
          <STATUS>Planned</STATUS>
          <ogr:geometryProperty><gml:LineString><gml:coordinates>2.259179,41.916398 2.249722,41.928333</gml:coordinates></gml:LineString></ogr:geometryProperty>
          </dlinks>
          </gml:featureMember>
          <gml:featureMember>
          <dlinks fid="123294">
          <NODE1_ID>1711</NODE1_ID>
          <NODE1_NAME>VicHabitat</NODE1_NAME>
          <NODE2_ID>56841</NODE2_ID>
          <NODE2_NAME>vicmetro</NODE2_NAME>
          <KMS>0.546</KMS>
          <LINK_TYPE>ap/client</LINK_TYPE>
          <STATUS>Working</STATUS>
          <ogr:geometryProperty><gml:LineString><gml:coordinates>2.249722,41.928333 2.250840,41.923492</gml:coordinates></gml:LineString></ogr:geometryProperty>
          </dlinks>
          </gml:featureMember>
          <gml:featureMember>
          <dlinks fid="123336">
          <NODE1_ID>77090</NODE1_ID>
          <NODE1_NAME>VICOMN</NODE1_NAME>
          <NODE2_ID>15036</NODE2_ID>
          <NODE2_NAME>VicSSantFerm</NODE2_NAME>
          <KMS>0.401</KMS>
          <LINK_TYPE>ap/client</LINK_TYPE>
          <STATUS>Planned</STATUS>
          <ogr:geometryProperty><gml:LineString><gml:coordinates>2.260171,41.916343 2.256746,41.913791</gml:coordinates></gml:LineString></ogr:geometryProperty>
          </dlinks>
          </gml:featureMember>
          <gml:featureMember>
          <dlinks fid="123339">
          <NODE1_ID>77075</NODE1_ID>
          <NODE1_NAME>VcCMPPmnmCltrl</NODE1_NAME>
          <NODE2_ID>40034</NODE2_ID>
          <NODE2_NAME>VicSubVigatana</NODE2_NAME>
          <KMS>0.383</KMS>
          <LINK_TYPE>ap/client</LINK_TYPE>
          <STATUS>Planned</STATUS>
          <ogr:geometryProperty><gml:LineString><gml:coordinates>2.259319,41.916640 2.258769,41.920062</gml:coordinates></gml:LineString></ogr:geometryProperty>
          </dlinks>
          </gml:featureMember>
          <gml:featureMember>
          <dlinks fid="123753">
          <NODE1_ID>40034</NODE1_ID>
          <NODE1_NAME>VicSubVigatana</NODE1_NAME>
          <NODE2_ID>77323</NODE2_ID>
          <NODE2_NAME>VicOMN10B</NODE2_NAME>
          <KMS>0.426</KMS>
          <LINK_TYPE>ap/client</LINK_TYPE>
          <STATUS>Working</STATUS>
          <ogr:geometryProperty><gml:LineString><gml:coordinates>2.258769,41.920062 2.260100,41.916354</gml:coordinates></gml:LineString></ogr:geometryProperty>
          </dlinks>
          </gml:featureMember>
          <gml:featureMember>
          <dlinks fid="123755">
          <NODE1_ID>77328</NODE1_ID>
          <NODE1_NAME>VicPaisosCatalans82</NODE1_NAME>
          <NODE2_ID>40034</NODE2_ID>
          <NODE2_NAME>VicSubVigatana</NODE2_NAME>
          <KMS>0.039</KMS>
          <LINK_TYPE>ap/client</LINK_TYPE>
          <STATUS>Planned</STATUS>
          <ogr:geometryProperty><gml:LineString><gml:coordinates>2.258339,41.919920 2.258769,41.920062</gml:coordinates></gml:LineString></ogr:geometryProperty>
          </dlinks>
          </gml:featureMember></ogr:FeatureCollection>