<?xml version="1.0" encoding="utf-8" ?>
<ogr:FeatureCollection
     xmlns:xsi="http://www.w3c.org/2001/XMLSchema-instance"
     xsi:schemaLocation=". dnodes.xsd"
     xmlns:ogr="http://ogr.maptools.org/"
     xmlns:gml="http://www.opengis.net/gml">
  <gml:boundedBy>
    <gml:Box>
      <gml:coord><gml:X>-0.269848</gml:X><gml:Y>38.776467</gml:Y></gml:coord>
      <gml:coord><gml:X>-0.250443</gml:X><gml:Y>38.795495</gml:Y></gml:coord>
    </gml:Box>
  </gml:boundedBy>
  <gml:featureMember>
    <dnodes fid="43856">
      <ogr:geometryProperty><gml:Point><gml:coordinates>-0.269720,38.776539</gml:coordinates></gml:Point></ogr:geometryProperty>
      <NODE_ID>43856</NODE_ID>
      <NODE_NAME>VALCLaFont10</NODE_NAME>
      <NODE_TYPE>client</NODE_TYPE>
      <STATUS>Planned</STATUS>
    </dnodes>
  </gml:featureMember>
  <gml:featureMember>
    <dnodes fid="43857">
      <ogr:geometryProperty><gml:Point><gml:coordinates>-0.269661,38.776539</gml:coordinates></gml:Point></ogr:geometryProperty>
      <NODE_ID>43857</NODE_ID>
      <NODE_NAME>VALCLaFont8</NODE_NAME>
      <NODE_TYPE>client</NODE_TYPE>
      <STATUS>Planned</STATUS>
    </dnodes>
  </gml:featureMember>
  <gml:featureMember>
    <dnodes fid="45559">
      <ogr:geometryProperty><gml:Point><gml:coordinates>-0.253297,38.793848</gml:coordinates></gml:Point></ogr:geometryProperty>
      <NODE_ID>45559</NODE_ID>
      <NODE_NAME>VALCVergeMiracle9</NODE_NAME>
      <NODE_TYPE>client</NODE_TYPE>
      <STATUS>Working</STATUS>
    </dnodes>
  </gml:featureMember>
  <gml:featureMember>
    <dnodes fid="42953">
      <ogr:geometryProperty><gml:Point><gml:coordinates>-0.250966,38.795238</gml:coordinates></gml:Point></ogr:geometryProperty>
      <NODE_ID>42953</NODE_ID>
      <NODE_NAME>VALCMoli8</NODE_NAME>
      <NODE_TYPE>client</NODE_TYPE>
      <STATUS>Planned</STATUS>
    </dnodes>
  </gml:featureMember>
  <gml:featureMember>
    <dnodes fid="41366">
      <ogr:geometryProperty><gml:Point><gml:coordinates>-0.251574,38.793438</gml:coordinates></gml:Point></ogr:geometryProperty>
      <NODE_ID>41366</NODE_ID>
      <NODE_NAME>VALCLaTorre22b</NODE_NAME>
      <NODE_TYPE>client</NODE_TYPE>
      <STATUS>Planned</STATUS>
    </dnodes>
  </gml:featureMember>
  <gml:featureMember>
    <dnodes fid="36762">
      <ogr:geometryProperty><gml:Point><gml:coordinates>-0.252342,38.794594</gml:coordinates></gml:Point></ogr:geometryProperty>
      <NODE_ID>36762</NODE_ID>
      <NODE_NAME>ValcalaNucli</NODE_NAME>
      <NODE_TYPE>Supernode</NODE_TYPE>
      <STATUS>Working</STATUS>
    </dnodes>
  </gml:featureMember>
  <gml:featureMember>
    <dnodes fid="42589">
      <ogr:geometryProperty><gml:Point><gml:coordinates>-0.252117,38.795431</gml:coordinates></gml:Point></ogr:geometryProperty>
      <NODE_ID>42589</NODE_ID>
      <NODE_NAME>VALCSantJosep30</NODE_NAME>
      <NODE_TYPE>client</NODE_TYPE>
      <STATUS>Working</STATUS>
    </dnodes>
  </gml:featureMember>
  <gml:featureMember>
    <dnodes fid="39172">
      <ogr:geometryProperty><gml:Point><gml:coordinates>-0.251704,38.794839</gml:coordinates></gml:Point></ogr:geometryProperty>
      <NODE_ID>39172</NODE_ID>
      <NODE_NAME>ValcalaCOOP</NODE_NAME>
      <NODE_TYPE>client</NODE_TYPE>
      <STATUS>Working</STATUS>
    </dnodes>
  </gml:featureMember>
  <gml:featureMember>
    <dnodes fid="39364">
      <ogr:geometryProperty><gml:Point><gml:coordinates>-0.250776,38.795495</gml:coordinates></gml:Point></ogr:geometryProperty>
      <NODE_ID>39364</NODE_ID>
      <NODE_NAME>VAlcalaEnrique</NODE_NAME>
      <NODE_TYPE>client</NODE_TYPE>
      <STATUS>Working</STATUS>
    </dnodes>
  </gml:featureMember>
  <gml:featureMember>
    <dnodes fid="39698">
      <ogr:geometryProperty><gml:Point><gml:coordinates>-0.252836,38.793906</gml:coordinates></gml:Point></ogr:geometryProperty>
      <NODE_ID>39698</NODE_ID>
      <NODE_NAME>VAlcala2Beniaia</NODE_NAME>
      <NODE_TYPE>Supernode</NODE_TYPE>
      <STATUS>Working</STATUS>
    </dnodes>
  </gml:featureMember>
  <gml:featureMember>
    <dnodes fid="41163">
      <ogr:geometryProperty><gml:Point><gml:coordinates>-0.253597,38.794157</gml:coordinates></gml:Point></ogr:geometryProperty>
      <NODE_ID>41163</NODE_ID>
      <NODE_NAME>VALCPaisValencia2</NODE_NAME>
      <NODE_TYPE>client</NODE_TYPE>
      <STATUS>Working</STATUS>
    </dnodes>
  </gml:featureMember>
  <gml:featureMember>
    <dnodes fid="41173">
      <ogr:geometryProperty><gml:Point><gml:coordinates>-0.251398,38.794918</gml:coordinates></gml:Point></ogr:geometryProperty>
      <NODE_ID>41173</NODE_ID>
      <NODE_NAME>VALCCarrerMoli12Fust</NODE_NAME>
      <NODE_TYPE>client</NODE_TYPE>
      <STATUS>Planned</STATUS>
    </dnodes>
  </gml:featureMember>
  <gml:featureMember>
    <dnodes fid="41368">
      <ogr:geometryProperty><gml:Point><gml:coordinates>-0.252763,38.793792</gml:coordinates></gml:Point></ogr:geometryProperty>
      <NODE_ID>41368</NODE_ID>
      <NODE_NAME>VALCElsAmetlers6</NODE_NAME>
      <NODE_TYPE>client</NODE_TYPE>
      <STATUS>Planned</STATUS>
    </dnodes>
  </gml:featureMember>
  <gml:featureMember>
    <dnodes fid="42406">
      <ogr:geometryProperty><gml:Point><gml:coordinates>-0.253099,38.793998</gml:coordinates></gml:Point></ogr:geometryProperty>
      <NODE_ID>42406</NODE_ID>
      <NODE_NAME>VALCMajor20</NODE_NAME>
      <NODE_TYPE>client</NODE_TYPE>
      <STATUS>Planned</STATUS>
    </dnodes>
  </gml:featureMember>
  <gml:featureMember>
    <dnodes fid="42407">
      <ogr:geometryProperty><gml:Point><gml:coordinates>-0.252149,38.795286</gml:coordinates></gml:Point></ogr:geometryProperty>
      <NODE_ID>42407</NODE_ID>
      <NODE_NAME>VALCSanJose13</NODE_NAME>
      <NODE_TYPE>client</NODE_TYPE>
      <STATUS>Working</STATUS>
    </dnodes>
  </gml:featureMember>
  <gml:featureMember>
    <dnodes fid="42439">
      <ogr:geometryProperty><gml:Point><gml:coordinates>-0.251889,38.795338</gml:coordinates></gml:Point></ogr:geometryProperty>
      <NODE_ID>42439</NODE_ID>
      <NODE_NAME>VALCSantJosep22</NODE_NAME>
      <NODE_TYPE>client</NODE_TYPE>
      <STATUS>Working</STATUS>
    </dnodes>
  </gml:featureMember>
  <gml:featureMember>
    <dnodes fid="42442">
      <ogr:geometryProperty><gml:Point><gml:coordinates>-0.254104,38.793960</gml:coordinates></gml:Point></ogr:geometryProperty>
      <NODE_ID>42442</NODE_ID>
      <NODE_NAME>VALCctraForestalSN</NODE_NAME>
      <NODE_TYPE>client</NODE_TYPE>
      <STATUS>Planned</STATUS>
    </dnodes>
  </gml:featureMember>
  <gml:featureMember>
    <dnodes fid="42443">
      <ogr:geometryProperty><gml:Point><gml:coordinates>-0.252616,38.794260</gml:coordinates></gml:Point></ogr:geometryProperty>
      <NODE_ID>42443</NODE_ID>
      <NODE_NAME>VALCMajor3</NODE_NAME>
      <NODE_TYPE>client</NODE_TYPE>
      <STATUS>Planned</STATUS>
    </dnodes>
  </gml:featureMember>
  <gml:featureMember>
    <dnodes fid="42444">
      <ogr:geometryProperty><gml:Point><gml:coordinates>-0.252104,38.795122</gml:coordinates></gml:Point></ogr:geometryProperty>
      <NODE_ID>42444</NODE_ID>
      <NODE_NAME>VALCSantJosep10</NODE_NAME>
      <NODE_TYPE>client</NODE_TYPE>
      <STATUS>Planned</STATUS>
    </dnodes>
  </gml:featureMember>
  <gml:featureMember>
    <dnodes fid="42445">
      <ogr:geometryProperty><gml:Point><gml:coordinates>-0.256290,38.794560</gml:coordinates></gml:Point></ogr:geometryProperty>
      <NODE_ID>42445</NODE_ID>
      <NODE_NAME>VALCampingAlcala</NODE_NAME>
      <NODE_TYPE>client</NODE_TYPE>
      <STATUS>Planned</STATUS>
    </dnodes>
  </gml:featureMember>
  <gml:featureMember>
    <dnodes fid="42449">
      <ogr:geometryProperty><gml:Point><gml:coordinates>-0.251661,38.793568</gml:coordinates></gml:Point></ogr:geometryProperty>
      <NODE_ID>42449</NODE_ID>
      <NODE_NAME>VALCLaTorre26</NODE_NAME>
      <NODE_TYPE>client</NODE_TYPE>
      <STATUS>Working</STATUS>
    </dnodes>
  </gml:featureMember>
  <gml:featureMember>
    <dnodes fid="42476">
      <ogr:geometryProperty><gml:Point><gml:coordinates>-0.252176,38.795239</gml:coordinates></gml:Point></ogr:geometryProperty>
      <NODE_ID>42476</NODE_ID>
      <NODE_NAME>VALCSantJosep9</NODE_NAME>
      <NODE_TYPE>client</NODE_TYPE>
      <STATUS>Working</STATUS>
    </dnodes>
  </gml:featureMember>
  <gml:featureMember>
    <dnodes fid="42609">
      <ogr:geometryProperty><gml:Point><gml:coordinates>-0.252927,38.794214</gml:coordinates></gml:Point></ogr:geometryProperty>
      <NODE_ID>42609</NODE_ID>
      <NODE_NAME>VALCMajor10</NODE_NAME>
      <NODE_TYPE>client</NODE_TYPE>
      <STATUS>Working</STATUS>
    </dnodes>
  </gml:featureMember>
  <gml:featureMember>
    <dnodes fid="42625">
      <ogr:geometryProperty><gml:Point><gml:coordinates>-0.251707,38.794047</gml:coordinates></gml:Point></ogr:geometryProperty>
      <NODE_ID>42625</NODE_ID>
      <NODE_NAME>VALCLatrre5</NODE_NAME>
      <NODE_TYPE>client</NODE_TYPE>
      <STATUS>Planned</STATUS>
    </dnodes>
  </gml:featureMember>
  <gml:featureMember>
    <dnodes fid="42634">
      <ogr:geometryProperty><gml:Point><gml:coordinates>-0.250647,38.795343</gml:coordinates></gml:Point></ogr:geometryProperty>
      <NODE_ID>42634</NODE_ID>
      <NODE_NAME>VALCMoli12</NODE_NAME>
      <NODE_TYPE>client</NODE_TYPE>
      <STATUS>Planned</STATUS>
    </dnodes>
  </gml:featureMember>
  <gml:featureMember>
    <dnodes fid="42636">
      <ogr:geometryProperty><gml:Point><gml:coordinates>-0.253002,38.793947</gml:coordinates></gml:Point></ogr:geometryProperty>
      <NODE_ID>42636</NODE_ID>
      <NODE_NAME>VALCMajor17B</NODE_NAME>
      <NODE_TYPE>client</NODE_TYPE>
      <STATUS>Planned</STATUS>
    </dnodes>
  </gml:featureMember>
  <gml:featureMember>
    <dnodes fid="42655">
      <ogr:geometryProperty><gml:Point><gml:coordinates>-0.252305,38.794237</gml:coordinates></gml:Point></ogr:geometryProperty>
      <NODE_ID>42655</NODE_ID>
      <NODE_NAME>VALCbisbevilaplana9</NODE_NAME>
      <NODE_TYPE>client</NODE_TYPE>
      <STATUS>Working</STATUS>
    </dnodes>
  </gml:featureMember>
  <gml:featureMember>
    <dnodes fid="42927">
      <ogr:geometryProperty><gml:Point><gml:coordinates>-0.268481,38.777062</gml:coordinates></gml:Point></ogr:geometryProperty>
      <NODE_ID>42927</NODE_ID>
      <NODE_NAME>VALCBaix3</NODE_NAME>
      <NODE_TYPE>client</NODE_TYPE>
      <STATUS>Planned</STATUS>
    </dnodes>
  </gml:featureMember>
  <gml:featureMember>
    <dnodes fid="42928">
      <ogr:geometryProperty><gml:Point><gml:coordinates>-0.268645,38.777048</gml:coordinates></gml:Point></ogr:geometryProperty>
      <NODE_ID>42928</NODE_ID>
      <NODE_NAME>VALCEsglesia6</NODE_NAME>
      <NODE_TYPE>client</NODE_TYPE>
      <STATUS>Planned</STATUS>
    </dnodes>
  </gml:featureMember>
  <gml:featureMember>
    <dnodes fid="42929">
      <ogr:geometryProperty><gml:Point><gml:coordinates>-0.252731,38.794321</gml:coordinates></gml:Point></ogr:geometryProperty>
      <NODE_ID>42929</NODE_ID>
      <NODE_NAME>VALCMajor4</NODE_NAME>
      <NODE_TYPE>client</NODE_TYPE>
      <STATUS>Planned</STATUS>
    </dnodes>
  </gml:featureMember>
  <gml:featureMember>
    <dnodes fid="42937">
      <ogr:geometryProperty><gml:Point><gml:coordinates>-0.252044,38.794074</gml:coordinates></gml:Point></ogr:geometryProperty>
      <NODE_ID>42937</NODE_ID>
      <NODE_NAME>VAlcalaLatorre8</NODE_NAME>
      <NODE_TYPE>client</NODE_TYPE>
      <STATUS>Working</STATUS>
    </dnodes>
  </gml:featureMember>
  <gml:featureMember>
    <dnodes fid="43218">
      <ogr:geometryProperty><gml:Point><gml:coordinates>-0.269640,38.776468</gml:coordinates></gml:Point></ogr:geometryProperty>
      <NODE_ID>43218</NODE_ID>
      <NODE_NAME>VALCLaFont5</NODE_NAME>
      <NODE_TYPE>client</NODE_TYPE>
      <STATUS>Planned</STATUS>
    </dnodes>
  </gml:featureMember>
  <gml:featureMember>
    <dnodes fid="43219">
      <ogr:geometryProperty><gml:Point><gml:coordinates>-0.269782,38.776467</gml:coordinates></gml:Point></ogr:geometryProperty>
      <NODE_ID>43219</NODE_ID>
      <NODE_NAME>VALCLaFont7</NODE_NAME>
      <NODE_TYPE>client</NODE_TYPE>
      <STATUS>Planned</STATUS>
    </dnodes>
  </gml:featureMember>
  <gml:featureMember>
    <dnodes fid="43222">
      <ogr:geometryProperty><gml:Point><gml:coordinates>-0.253517,38.793921</gml:coordinates></gml:Point></ogr:geometryProperty>
      <NODE_ID>43222</NODE_ID>
      <NODE_NAME>VALCVergeMiracle3</NODE_NAME>
      <NODE_TYPE>client</NODE_TYPE>
      <STATUS>Planned</STATUS>
    </dnodes>
  </gml:featureMember>
  <gml:featureMember>
    <dnodes fid="43633">
      <ogr:geometryProperty><gml:Point><gml:coordinates>-0.268913,38.777182</gml:coordinates></gml:Point></ogr:geometryProperty>
      <NODE_ID>43633</NODE_ID>
      <NODE_NAME>VALCPIglesia4</NODE_NAME>
      <NODE_TYPE>client</NODE_TYPE>
      <STATUS>Planned</STATUS>
    </dnodes>
  </gml:featureMember>
  <gml:featureMember>
    <dnodes fid="43860">
      <ogr:geometryProperty><gml:Point><gml:coordinates>-0.269278,38.776572</gml:coordinates></gml:Point></ogr:geometryProperty>
      <NODE_ID>43860</NODE_ID>
      <NODE_NAME>VALCLaFont2A</NODE_NAME>
      <NODE_TYPE>client</NODE_TYPE>
      <STATUS>Planned</STATUS>
    </dnodes>
  </gml:featureMember>
  <gml:featureMember>
    <dnodes fid="47152">
      <ogr:geometryProperty><gml:Point><gml:coordinates>-0.252299,38.794914</gml:coordinates></gml:Point></ogr:geometryProperty>
      <NODE_ID>47152</NODE_ID>
      <NODE_NAME>AlcalaSanJose5</NODE_NAME>
      <NODE_TYPE>N_A</NODE_TYPE>
      <STATUS>Planned</STATUS>
    </dnodes>
  </gml:featureMember>
  <gml:featureMember>
    <dnodes fid="44174">
      <ogr:geometryProperty><gml:Point><gml:coordinates>-0.251784,38.793915</gml:coordinates></gml:Point></ogr:geometryProperty>
      <NODE_ID>44174</NODE_ID>
      <NODE_NAME>VALCLaTorre6</NODE_NAME>
      <NODE_TYPE>client</NODE_TYPE>
      <STATUS>Working</STATUS>
    </dnodes>
  </gml:featureMember>
  <gml:featureMember>
    <dnodes fid="44176">
      <ogr:geometryProperty><gml:Point><gml:coordinates>-0.251763,38.793831</gml:coordinates></gml:Point></ogr:geometryProperty>
      <NODE_ID>44176</NODE_ID>
      <NODE_NAME>VALCLaTorre12</NODE_NAME>
      <NODE_TYPE>client</NODE_TYPE>
      <STATUS>Planned</STATUS>
    </dnodes>
  </gml:featureMember>
  <gml:featureMember>
    <dnodes fid="44193">
      <ogr:geometryProperty><gml:Point><gml:coordinates>-0.251763,38.794015</gml:coordinates></gml:Point></ogr:geometryProperty>
      <NODE_ID>44193</NODE_ID>
      <NODE_NAME>VALCLatorre4</NODE_NAME>
      <NODE_TYPE>client</NODE_TYPE>
      <STATUS>Working</STATUS>
    </dnodes>
  </gml:featureMember>
  <gml:featureMember>
    <dnodes fid="44373">
      <ogr:geometryProperty><gml:Point><gml:coordinates>-0.268068,38.777200</gml:coordinates></gml:Point></ogr:geometryProperty>
      <NODE_ID>44373</NODE_ID>
      <NODE_NAME>VALCBaix17</NODE_NAME>
      <NODE_TYPE>client</NODE_TYPE>
      <STATUS>Planned</STATUS>
    </dnodes>
  </gml:featureMember>
  <gml:featureMember>
    <dnodes fid="44375">
      <ogr:geometryProperty><gml:Point><gml:coordinates>-0.269848,38.776475</gml:coordinates></gml:Point></ogr:geometryProperty>
      <NODE_ID>44375</NODE_ID>
      <NODE_NAME>VALCLaFont9</NODE_NAME>
      <NODE_TYPE>client</NODE_TYPE>
      <STATUS>Planned</STATUS>
    </dnodes>
  </gml:featureMember>
  <gml:featureMember>
    <dnodes fid="44376">
      <ogr:geometryProperty><gml:Point><gml:coordinates>-0.268579,38.776958</gml:coordinates></gml:Point></ogr:geometryProperty>
      <NODE_ID>44376</NODE_ID>
      <NODE_NAME>VALCBaix4</NODE_NAME>
      <NODE_TYPE>client</NODE_TYPE>
      <STATUS>Planned</STATUS>
    </dnodes>
  </gml:featureMember>
  <gml:featureMember>
    <dnodes fid="44672">
      <ogr:geometryProperty><gml:Point><gml:coordinates>-0.251772,38.793878</gml:coordinates></gml:Point></ogr:geometryProperty>
      <NODE_ID>44672</NODE_ID>
      <NODE_NAME>VALCLaTorre19</NODE_NAME>
      <NODE_TYPE>client</NODE_TYPE>
      <STATUS>Planned</STATUS>
    </dnodes>
  </gml:featureMember>
  <gml:featureMember>
    <dnodes fid="44971">
      <ogr:geometryProperty><gml:Point><gml:coordinates>-0.254947,38.794803</gml:coordinates></gml:Point></ogr:geometryProperty>
      <NODE_ID>44971</NODE_ID>
      <NODE_NAME>VALCParc313</NODE_NAME>
      <NODE_TYPE>client</NODE_TYPE>
      <STATUS>Working</STATUS>
    </dnodes>
  </gml:featureMember>
  <gml:featureMember>
    <dnodes fid="45453">
      <ogr:geometryProperty><gml:Point><gml:coordinates>-0.252205,38.795202</gml:coordinates></gml:Point></ogr:geometryProperty>
      <NODE_ID>45453</NODE_ID>
      <NODE_NAME>VALCSantJosep7</NODE_NAME>
      <NODE_TYPE>client</NODE_TYPE>
      <STATUS>Planned</STATUS>
    </dnodes>
  </gml:featureMember>
  <gml:featureMember>
    <dnodes fid="45802">
      <ogr:geometryProperty><gml:Point><gml:coordinates>-0.268346,38.777096</gml:coordinates></gml:Point></ogr:geometryProperty>
      <NODE_ID>45802</NODE_ID>
      <NODE_NAME>VALCBaix9</NODE_NAME>
      <NODE_TYPE>client</NODE_TYPE>
      <STATUS>Planned</STATUS>
    </dnodes>
  </gml:featureMember>
  <gml:featureMember>
    <dnodes fid="46460">
      <ogr:geometryProperty><gml:Point><gml:coordinates>-0.252423,38.794444</gml:coordinates></gml:Point></ogr:geometryProperty>
      <NODE_ID>46460</NODE_ID>
      <NODE_NAME>VALCItinerante</NODE_NAME>
      <NODE_TYPE>client</NODE_TYPE>
      <STATUS>Planned</STATUS>
    </dnodes>
  </gml:featureMember>
  <gml:featureMember>
    <dnodes fid="46530">
      <ogr:geometryProperty><gml:Point><gml:coordinates>-0.251446,38.793857</gml:coordinates></gml:Point></ogr:geometryProperty>
      <NODE_ID>46530</NODE_ID>
      <NODE_NAME>VALCLaTorre7</NODE_NAME>
      <NODE_TYPE>client</NODE_TYPE>
      <STATUS>Planned</STATUS>
    </dnodes>
  </gml:featureMember>
  <gml:featureMember>
    <dnodes fid="48559">
      <ogr:geometryProperty><gml:Point><gml:coordinates>-0.252004,38.795449</gml:coordinates></gml:Point></ogr:geometryProperty>
      <NODE_ID>48559</NODE_ID>
      <NODE_NAME>VALCSanJose28</NODE_NAME>
      <NODE_TYPE>client</NODE_TYPE>
      <STATUS>Working</STATUS>
    </dnodes>
  </gml:featureMember>
  <gml:featureMember>
    <dnodes fid="48560">
      <ogr:geometryProperty><gml:Point><gml:coordinates>-0.250443,38.795428</gml:coordinates></gml:Point></ogr:geometryProperty>
      <NODE_ID>48560</NODE_ID>
      <NODE_NAME>VALCCamiMoli14</NODE_NAME>
      <NODE_TYPE>client</NODE_TYPE>
      <STATUS>Working</STATUS>
    </dnodes>
  </gml:featureMember>
  <gml:featureMember>
    <dnodes fid="48561">
      <ogr:geometryProperty><gml:Point><gml:coordinates>-0.251701,38.793653</gml:coordinates></gml:Point></ogr:geometryProperty>
      <NODE_ID>48561</NODE_ID>
      <NODE_NAME>VALCAmetlers13</NODE_NAME>
      <NODE_TYPE>client</NODE_TYPE>
      <STATUS>Working</STATUS>
    </dnodes>
  </gml:featureMember>
  <gml:featureMember>
    <dnodes fid="48562">
      <ogr:geometryProperty><gml:Point><gml:coordinates>-0.252782,38.794195</gml:coordinates></gml:Point></ogr:geometryProperty>
      <NODE_ID>48562</NODE_ID>
      <NODE_NAME>VALCMajor9a</NODE_NAME>
      <NODE_TYPE>client</NODE_TYPE>
      <STATUS>Dropped</STATUS>
    </dnodes>
  </gml:featureMember>
  <gml:featureMember>
    <dnodes fid="48563">
      <ogr:geometryProperty><gml:Point><gml:coordinates>-0.252176,38.794937</gml:coordinates></gml:Point></ogr:geometryProperty>
      <NODE_ID>48563</NODE_ID>
      <NODE_NAME>VALCVirgenPilar1</NODE_NAME>
      <NODE_TYPE>client</NODE_TYPE>
      <STATUS>Working</STATUS>
    </dnodes>
  </gml:featureMember>
  <gml:featureMember>
    <dnodes fid="48794">
      <ogr:geometryProperty><gml:Point><gml:coordinates>-0.252364,38.794929</gml:coordinates></gml:Point></ogr:geometryProperty>
      <NODE_ID>48794</NODE_ID>
      <NODE_NAME>valcala-vergepilar6</NODE_NAME>
      <NODE_TYPE>client</NODE_TYPE>
      <STATUS>Working</STATUS>
    </dnodes>
  </gml:featureMember>
  <gml:featureMember>
    <dnodes fid="49581">
      <ogr:geometryProperty><gml:Point><gml:coordinates>-0.251720,38.793605</gml:coordinates></gml:Point></ogr:geometryProperty>
      <NODE_ID>49581</NODE_ID>
      <NODE_NAME>VALCElsAmetlers26</NODE_NAME>
      <NODE_TYPE>client</NODE_TYPE>
      <STATUS>Planned</STATUS>
    </dnodes>
  </gml:featureMember>
  <gml:featureMember>
    <dnodes fid="49794">
      <ogr:geometryProperty><gml:Point><gml:coordinates>-0.250452,38.794938</gml:coordinates></gml:Point></ogr:geometryProperty>
      <NODE_ID>49794</NODE_ID>
      <NODE_NAME>VALCXaletNorman</NODE_NAME>
      <NODE_TYPE>client</NODE_TYPE>
      <STATUS>Working</STATUS>
    </dnodes>
  </gml:featureMember>
  <gml:featureMember>
    <dnodes fid="50061">
      <ogr:geometryProperty><gml:Point><gml:coordinates>-0.252868,38.793751</gml:coordinates></gml:Point></ogr:geometryProperty>
      <NODE_ID>50061</NODE_ID>
      <NODE_NAME>VALCAmetlers2</NODE_NAME>
      <NODE_TYPE>client</NODE_TYPE>
      <STATUS>Planned</STATUS>
    </dnodes>
  </gml:featureMember>
  <gml:featureMember>
    <dnodes fid="50339">
      <ogr:geometryProperty><gml:Point><gml:coordinates>-0.251943,38.795404</gml:coordinates></gml:Point></ogr:geometryProperty>
      <NODE_ID>50339</NODE_ID>
      <NODE_NAME>VALCSantJosep24</NODE_NAME>
      <NODE_TYPE>client</NODE_TYPE>
      <STATUS>Working</STATUS>
    </dnodes>
  </gml:featureMember>
  <gml:featureMember>
    <dnodes fid="50731">
      <ogr:geometryProperty><gml:Point><gml:coordinates>-0.268237,38.777009</gml:coordinates></gml:Point></ogr:geometryProperty>
      <NODE_ID>50731</NODE_ID>
      <NODE_NAME>VALCBaix8</NODE_NAME>
      <NODE_TYPE>client</NODE_TYPE>
      <STATUS>Planned</STATUS>
    </dnodes>
  </gml:featureMember>
  <gml:featureMember>
    <dnodes fid="55642">
      <ogr:geometryProperty><gml:Point><gml:coordinates>-0.251527,38.793630</gml:coordinates></gml:Point></ogr:geometryProperty>
      <NODE_ID>55642</NODE_ID>
      <NODE_NAME>VallAlcalatorre120</NODE_NAME>
      <NODE_TYPE>N_A</NODE_TYPE>
      <STATUS>Planned</STATUS>
    </dnodes>
  </gml:featureMember>
  <gml:featureMember>
    <dnodes fid="56887">
      <ogr:geometryProperty><gml:Point><gml:coordinates>-0.268771,38.777128</gml:coordinates></gml:Point></ogr:geometryProperty>
      <NODE_ID>56887</NODE_ID>
      <NODE_NAME>VALCEsglesia5</NODE_NAME>
      <NODE_TYPE>client</NODE_TYPE>
      <STATUS>Working</STATUS>
    </dnodes>
  </gml:featureMember>
  <gml:featureMember>
    <dnodes fid="59930">
      <ogr:geometryProperty><gml:Point><gml:coordinates>-0.252369,38.794941</gml:coordinates></gml:Point></ogr:geometryProperty>
      <NODE_ID>59930</NODE_ID>
      <NODE_NAME>VALCVergePilar6B</NODE_NAME>
      <NODE_TYPE>client</NODE_TYPE>
      <STATUS>Planned</STATUS>
    </dnodes>
  </gml:featureMember>
  <gml:featureMember>
    <dnodes fid="63546">
      <ogr:geometryProperty><gml:Point><gml:coordinates>-0.252270,38.794582</gml:coordinates></gml:Point></ogr:geometryProperty>
      <NODE_ID>63546</NODE_ID>
      <NODE_NAME>VALCBisbeVilaplana5</NODE_NAME>
      <NODE_TYPE>client</NODE_TYPE>
      <STATUS>Working</STATUS>
    </dnodes>
  </gml:featureMember>
  <gml:featureMember>
    <dnodes fid="66685">
      <ogr:geometryProperty><gml:Point><gml:coordinates>-0.252374,38.794354</gml:coordinates></gml:Point></ogr:geometryProperty>
      <NODE_ID>66685</NODE_ID>
      <NODE_NAME>VALCHotelLaFont</NODE_NAME>
      <NODE_TYPE>client</NODE_TYPE>
      <STATUS>Working</STATUS>
    </dnodes>
  </gml:featureMember>
  <gml:featureMember>
    <dnodes fid="66738">
      <ogr:geometryProperty><gml:Point><gml:coordinates>-0.268698,38.776874</gml:coordinates></gml:Point></ogr:geometryProperty>
      <NODE_ID>66738</NODE_ID>
      <NODE_NAME>VALCDespoblados3</NODE_NAME>
      <NODE_TYPE>client</NODE_TYPE>
      <STATUS>Working</STATUS>
    </dnodes>
  </gml:featureMember>
  <gml:featureMember>
    <dnodes fid="69845">
      <ogr:geometryProperty><gml:Point><gml:coordinates>-0.252737,38.794218</gml:coordinates></gml:Point></ogr:geometryProperty>
      <NODE_ID>69845</NODE_ID>
      <NODE_NAME>VALCEdBadia</NODE_NAME>
      <NODE_TYPE>client</NODE_TYPE>
      <STATUS>Working</STATUS>
    </dnodes>
  </gml:featureMember>
</ogr:FeatureCollection>