<?xml version="1.0" encoding="utf-8" ?>
<ogr:FeatureCollection
     xmlns:xsi="http://www.w3c.org/2001/XMLSchema-instance"
     xsi:schemaLocation=". dnodes.xsd"
     xmlns:ogr="http://ogr.maptools.org/"
     xmlns:gml="http://www.opengis.net/gml">
  <gml:boundedBy>
    <gml:Box>
      <gml:coord><gml:X>-0.330660</gml:X><gml:Y>39.877224</gml:Y></gml:coord>
      <gml:coord><gml:X>-0.056216</gml:X><gml:Y>40.172770</gml:Y></gml:coord>
    </gml:Box>
  </gml:boundedBy>
  <gml:featureMember>
    <dnodes fid="47841">
      <ogr:geometryProperty><gml:Point><gml:coordinates>-0.284765,40.133807</gml:coordinates></gml:Point></ogr:geometryProperty>
      <NODE_ID>47841</NODE_ID>
      <NODE_NAME>LLCSr1</NODE_NAME>
      <NODE_TYPE>client</NODE_TYPE>
      <STATUS>Planned</STATUS>
    </dnodes>
  </gml:featureMember>
  <gml:featureMember>
    <dnodes fid="44892">
      <ogr:geometryProperty><gml:Point><gml:coordinates>-0.319126,40.095753</gml:coordinates></gml:Point></ogr:geometryProperty>
      <NODE_ID>44892</NODE_ID>
      <NODE_NAME>LlucMasJuncar</NODE_NAME>
      <NODE_TYPE>N_A</NODE_TYPE>
      <STATUS>Planned</STATUS>
    </dnodes>
  </gml:featureMember>
  <gml:featureMember>
    <dnodes fid="61639">
      <ogr:geometryProperty><gml:Point><gml:coordinates>-0.279584,40.139263</gml:coordinates></gml:Point></ogr:geometryProperty>
      <NODE_ID>61639</NODE_ID>
      <NODE_NAME>SROQ49</NODE_NAME>
      <NODE_TYPE>client</NODE_TYPE>
      <STATUS>Planned</STATUS>
    </dnodes>
  </gml:featureMember>
  <gml:featureMember>
    <dnodes fid="40298">
      <ogr:geometryProperty><gml:Point><gml:coordinates>-0.279207,40.135607</gml:coordinates></gml:Point></ogr:geometryProperty>
      <NODE_ID>40298</NODE_ID>
      <NODE_NAME>LLuc-Social</NODE_NAME>
      <NODE_TYPE>Supernode</NODE_TYPE>
      <STATUS>Testing</STATUS>
    </dnodes>
  </gml:featureMember>
  <gml:featureMember>
    <dnodes fid="51346">
      <ogr:geometryProperty><gml:Point><gml:coordinates>-0.280396,40.136547</gml:coordinates></gml:Point></ogr:geometryProperty>
      <NODE_ID>51346</NODE_ID>
      <NODE_NAME>EST49</NODE_NAME>
      <NODE_TYPE>client</NODE_TYPE>
      <STATUS>Planned</STATUS>
    </dnodes>
  </gml:featureMember>
  <gml:featureMember>
    <dnodes fid="36944">
      <ogr:geometryProperty><gml:Point><gml:coordinates>-0.330660,40.135660</gml:coordinates></gml:Point></ogr:geometryProperty>
      <NODE_ID>36944</NODE_ID>
      <NODE_NAME>Lluc-MasMagdalena</NODE_NAME>
      <NODE_TYPE>N_A</NODE_TYPE>
      <STATUS>Planned</STATUS>
    </dnodes>
  </gml:featureMember>
  <gml:featureMember>
    <dnodes fid="39080">
      <ogr:geometryProperty><gml:Point><gml:coordinates>-0.279363,40.139316</gml:coordinates></gml:Point></ogr:geometryProperty>
      <NODE_ID>39080</NODE_ID>
      <NODE_NAME>LLuc-Castillo</NODE_NAME>
      <NODE_TYPE>Supernode</NODE_TYPE>
      <STATUS>Testing</STATUS>
    </dnodes>
  </gml:featureMember>
  <gml:featureMember>
    <dnodes fid="39081">
      <ogr:geometryProperty><gml:Point><gml:coordinates>-0.280141,40.137945</gml:coordinates></gml:Point></ogr:geometryProperty>
      <NODE_ID>39081</NODE_ID>
      <NODE_NAME>LLuc-Ajuntament</NODE_NAME>
      <NODE_TYPE>Supernode</NODE_TYPE>
      <STATUS>Testing</STATUS>
    </dnodes>
  </gml:featureMember>
  <gml:featureMember>
    <dnodes fid="39082">
      <ogr:geometryProperty><gml:Point><gml:coordinates>-0.303106,40.172770</gml:coordinates></gml:Point></ogr:geometryProperty>
      <NODE_ID>39082</NODE_ID>
      <NODE_NAME>LLuc-MasCosta</NODE_NAME>
      <NODE_TYPE>N_A</NODE_TYPE>
      <STATUS>Planned</STATUS>
    </dnodes>
  </gml:featureMember>
  <gml:featureMember>
    <dnodes fid="39226">
      <ogr:geometryProperty><gml:Point><gml:coordinates>-0.322954,40.135074</gml:coordinates></gml:Point></ogr:geometryProperty>
      <NODE_ID>39226</NODE_ID>
      <NODE_NAME>Lluc-MasdeMadalena2</NODE_NAME>
      <NODE_TYPE>N_A</NODE_TYPE>
      <STATUS>Planned</STATUS>
    </dnodes>
  </gml:featureMember>
  <gml:featureMember>
    <dnodes fid="46235">
      <ogr:geometryProperty><gml:Point><gml:coordinates>-0.281729,40.137229</gml:coordinates></gml:Point></ogr:geometryProperty>
      <NODE_ID>46235</NODE_ID>
      <NODE_NAME>LLucDuqTetuan48</NODE_NAME>
      <NODE_TYPE>client</NODE_TYPE>
      <STATUS>Working</STATUS>
    </dnodes>
  </gml:featureMember>
  <gml:featureMember>
    <dnodes fid="40032">
      <ogr:geometryProperty><gml:Point><gml:coordinates>-0.281231,40.135221</gml:coordinates></gml:Point></ogr:geometryProperty>
      <NODE_ID>40032</NODE_ID>
      <NODE_NAME>Lluc-fl10</NODE_NAME>
      <NODE_TYPE>client</NODE_TYPE>
      <STATUS>Working</STATUS>
    </dnodes>
  </gml:featureMember>
  <gml:featureMember>
    <dnodes fid="59090">
      <ogr:geometryProperty><gml:Point><gml:coordinates>-0.272523,40.140282</gml:coordinates></gml:Point></ogr:geometryProperty>
      <NODE_ID>59090</NODE_ID>
      <NODE_NAME>RIUPAC</NODE_NAME>
      <NODE_TYPE>client</NODE_TYPE>
      <STATUS>Planned</STATUS>
    </dnodes>
  </gml:featureMember>
  <gml:featureMember>
    <dnodes fid="43096">
      <ogr:geometryProperty><gml:Point><gml:coordinates>-0.280838,40.136349</gml:coordinates></gml:Point></ogr:geometryProperty>
      <NODE_ID>43096</NODE_ID>
      <NODE_NAME>LLucGonzaloPuerto12</NODE_NAME>
      <NODE_TYPE>client</NODE_TYPE>
      <STATUS>Planned</STATUS>
    </dnodes>
  </gml:featureMember>
  <gml:featureMember>
    <dnodes fid="45734">
      <ogr:geometryProperty><gml:Point><gml:coordinates>-0.318571,40.076150</gml:coordinates></gml:Point></ogr:geometryProperty>
      <NODE_ID>45734</NODE_ID>
      <NODE_NAME>LLUCENA_Masdelmoro</NODE_NAME>
      <NODE_TYPE>N_A</NODE_TYPE>
      <STATUS>Planned</STATUS>
    </dnodes>
  </gml:featureMember>
  <gml:featureMember>
    <dnodes fid="60283">
      <ogr:geometryProperty><gml:Point><gml:coordinates>-0.279264,40.138936</gml:coordinates></gml:Point></ogr:geometryProperty>
      <NODE_ID>60283</NODE_ID>
      <NODE_NAME>MEDNEB30</NODE_NAME>
      <NODE_TYPE>client</NODE_TYPE>
      <STATUS>Planned</STATUS>
    </dnodes>
  </gml:featureMember>
  <gml:featureMember>
    <dnodes fid="45836">
      <ogr:geometryProperty><gml:Point><gml:coordinates>-0.317439,40.099080</gml:coordinates></gml:Point></ogr:geometryProperty>
      <NODE_ID>45836</NODE_ID>
      <NODE_NAME>LVDJCorralet</NODE_NAME>
      <NODE_TYPE>N_A</NODE_TYPE>
      <STATUS>Planned</STATUS>
    </dnodes>
  </gml:featureMember>
  <gml:featureMember>
    <dnodes fid="48127">
      <ogr:geometryProperty><gml:Point><gml:coordinates>-0.280173,40.136989</gml:coordinates></gml:Point></ogr:geometryProperty>
      <NODE_ID>48127</NODE_ID>
      <NODE_NAME>LlucCav33</NODE_NAME>
      <NODE_TYPE>N_A</NODE_TYPE>
      <STATUS>Planned</STATUS>
    </dnodes>
  </gml:featureMember>
  <gml:featureMember>
    <dnodes fid="48128">
      <ogr:geometryProperty><gml:Point><gml:coordinates>-0.280108,40.137088</gml:coordinates></gml:Point></ogr:geometryProperty>
      <NODE_ID>48128</NODE_ID>
      <NODE_NAME>LlucenaCavaller33</NODE_NAME>
      <NODE_TYPE>client</NODE_TYPE>
      <STATUS>Working</STATUS>
    </dnodes>
  </gml:featureMember>
  <gml:featureMember>
    <dnodes fid="48171">
      <ogr:geometryProperty><gml:Point><gml:coordinates>-0.281305,40.136973</gml:coordinates></gml:Point></ogr:geometryProperty>
      <NODE_ID>48171</NODE_ID>
      <NODE_NAME>LlucEras43</NODE_NAME>
      <NODE_TYPE>client</NODE_TYPE>
      <STATUS>Working</STATUS>
    </dnodes>
  </gml:featureMember>
  <gml:featureMember>
    <dnodes fid="48591">
      <ogr:geometryProperty><gml:Point><gml:coordinates>-0.286310,40.135224</gml:coordinates></gml:Point></ogr:geometryProperty>
      <NODE_ID>48591</NODE_ID>
      <NODE_NAME>SR1</NODE_NAME>
      <NODE_TYPE>client</NODE_TYPE>
      <STATUS>Working</STATUS>
    </dnodes>
  </gml:featureMember>
  <gml:featureMember>
    <dnodes fid="48954">
      <ogr:geometryProperty><gml:Point><gml:coordinates>-0.280835,40.134854</gml:coordinates></gml:Point></ogr:geometryProperty>
      <NODE_ID>48954</NODE_ID>
      <NODE_NAME>Avda.FerLeo10</NODE_NAME>
      <NODE_TYPE>client</NODE_TYPE>
      <STATUS>Planned</STATUS>
    </dnodes>
  </gml:featureMember>
  <gml:featureMember>
    <dnodes fid="49803">
      <ogr:geometryProperty><gml:Point><gml:coordinates>-0.280776,40.137637</gml:coordinates></gml:Point></ogr:geometryProperty>
      <NODE_ID>49803</NODE_ID>
      <NODE_NAME>LUCparra10</NODE_NAME>
      <NODE_TYPE>client</NODE_TYPE>
      <STATUS>Testing</STATUS>
    </dnodes>
  </gml:featureMember>
  <gml:featureMember>
    <dnodes fid="50298">
      <ogr:geometryProperty><gml:Point><gml:coordinates>-0.280441,40.138128</gml:coordinates></gml:Point></ogr:geometryProperty>
      <NODE_ID>50298</NODE_ID>
      <NODE_NAME>PlaE5</NODE_NAME>
      <NODE_TYPE>client</NODE_TYPE>
      <STATUS>Planned</STATUS>
    </dnodes>
  </gml:featureMember>
  <gml:featureMember>
    <dnodes fid="50674">
      <ogr:geometryProperty><gml:Point><gml:coordinates>-0.280715,40.138050</gml:coordinates></gml:Point></ogr:geometryProperty>
      <NODE_ID>50674</NODE_ID>
      <NODE_NAME>PlCan2</NODE_NAME>
      <NODE_TYPE>client</NODE_TYPE>
      <STATUS>Planned</STATUS>
    </dnodes>
  </gml:featureMember>
  <gml:featureMember>
    <dnodes fid="52656">
      <ogr:geometryProperty><gml:Point><gml:coordinates>-0.280994,40.135863</gml:coordinates></gml:Point></ogr:geometryProperty>
      <NODE_ID>52656</NODE_ID>
      <NODE_NAME>AVDFER22</NODE_NAME>
      <NODE_TYPE>client</NODE_TYPE>
      <STATUS>Planned</STATUS>
    </dnodes>
  </gml:featureMember>
  <gml:featureMember>
    <dnodes fid="51572">
      <ogr:geometryProperty><gml:Point><gml:coordinates>-0.281659,40.137124</gml:coordinates></gml:Point></ogr:geometryProperty>
      <NODE_ID>51572</NODE_ID>
      <NODE_NAME>MEDNEB31</NODE_NAME>
      <NODE_TYPE>client</NODE_TYPE>
      <STATUS>Working</STATUS>
    </dnodes>
  </gml:featureMember>
  <gml:featureMember>
    <dnodes fid="51845">
      <ogr:geometryProperty><gml:Point><gml:coordinates>-0.281238,40.136869</gml:coordinates></gml:Point></ogr:geometryProperty>
      <NODE_ID>51845</NODE_ID>
      <NODE_NAME>RS15</NODE_NAME>
      <NODE_TYPE>client</NODE_TYPE>
      <STATUS>Planned</STATUS>
    </dnodes>
  </gml:featureMember>
  <gml:featureMember>
    <dnodes fid="52249">
      <ogr:geometryProperty><gml:Point><gml:coordinates>-0.281396,40.137252</gml:coordinates></gml:Point></ogr:geometryProperty>
      <NODE_ID>52249</NODE_ID>
      <NODE_NAME>ACEQ2</NODE_NAME>
      <NODE_TYPE>client</NODE_TYPE>
      <STATUS>Planned</STATUS>
    </dnodes>
  </gml:featureMember>
  <gml:featureMember>
    <dnodes fid="52250">
      <ogr:geometryProperty><gml:Point><gml:coordinates>-0.280683,40.136092</gml:coordinates></gml:Point></ogr:geometryProperty>
      <NODE_ID>52250</NODE_ID>
      <NODE_NAME>HOGJUB</NODE_NAME>
      <NODE_TYPE>client</NODE_TYPE>
      <STATUS>Planned</STATUS>
    </dnodes>
  </gml:featureMember>
  <gml:featureMember>
    <dnodes fid="53111">
      <ogr:geometryProperty><gml:Point><gml:coordinates>-0.278757,40.135150</gml:coordinates></gml:Point></ogr:geometryProperty>
      <NODE_ID>53111</NODE_ID>
      <NODE_NAME>AVDCATENR</NODE_NAME>
      <NODE_TYPE>client</NODE_TYPE>
      <STATUS>Planned</STATUS>
    </dnodes>
  </gml:featureMember>
  <gml:featureMember>
    <dnodes fid="53050">
      <ogr:geometryProperty><gml:Point><gml:coordinates>-0.278529,40.139535</gml:coordinates></gml:Point></ogr:geometryProperty>
      <NODE_ID>53050</NODE_ID>
      <NODE_NAME>ADZTERE</NODE_NAME>
      <NODE_TYPE>client</NODE_TYPE>
      <STATUS>Planned</STATUS>
    </dnodes>
  </gml:featureMember>
  <gml:featureMember>
    <dnodes fid="54301">
      <ogr:geometryProperty><gml:Point><gml:coordinates>-0.279783,40.139432</gml:coordinates></gml:Point></ogr:geometryProperty>
      <NODE_ID>54301</NODE_ID>
      <NODE_NAME>nodolucena</NODE_NAME>
      <NODE_TYPE>client</NODE_TYPE>
      <STATUS>Planned</STATUS>
    </dnodes>
  </gml:featureMember>
  <gml:featureMember>
    <dnodes fid="54502">
      <ogr:geometryProperty><gml:Point><gml:coordinates>-0.279864,40.138330</gml:coordinates></gml:Point></ogr:geometryProperty>
      <NODE_ID>54502</NODE_ID>
      <NODE_NAME>PLZSPN2</NODE_NAME>
      <NODE_TYPE>Supernode</NODE_TYPE>
      <STATUS>Planned</STATUS>
    </dnodes>
  </gml:featureMember>
  <gml:featureMember>
    <dnodes fid="55453">
      <ogr:geometryProperty><gml:Point><gml:coordinates>-0.281230,40.137518</gml:coordinates></gml:Point></ogr:geometryProperty>
      <NODE_ID>55453</NODE_ID>
      <NODE_NAME>Lluc-ddt15</NODE_NAME>
      <NODE_TYPE>client</NODE_TYPE>
      <STATUS>Working</STATUS>
    </dnodes>
  </gml:featureMember>
  <gml:featureMember>
    <dnodes fid="55458">
      <ogr:geometryProperty><gml:Point><gml:coordinates>-0.281468,40.136716</gml:coordinates></gml:Point></ogr:geometryProperty>
      <NODE_ID>55458</NODE_ID>
      <NODE_NAME>CTTER3</NODE_NAME>
      <NODE_TYPE>Supernode</NODE_TYPE>
      <STATUS>Planned</STATUS>
    </dnodes>
  </gml:featureMember>
  <gml:featureMember>
    <dnodes fid="55556">
      <ogr:geometryProperty><gml:Point><gml:coordinates>-0.280583,40.136870</gml:coordinates></gml:Point></ogr:geometryProperty>
      <NODE_ID>55556</NODE_ID>
      <NODE_NAME>ERAS2</NODE_NAME>
      <NODE_TYPE>client</NODE_TYPE>
      <STATUS>Planned</STATUS>
    </dnodes>
  </gml:featureMember>
  <gml:featureMember>
    <dnodes fid="56009">
      <ogr:geometryProperty><gml:Point><gml:coordinates>-0.280551,40.136200</gml:coordinates></gml:Point></ogr:geometryProperty>
      <NODE_ID>56009</NODE_ID>
      <NODE_NAME>GONPUE3</NODE_NAME>
      <NODE_TYPE>client</NODE_TYPE>
      <STATUS>Planned</STATUS>
    </dnodes>
  </gml:featureMember>
  <gml:featureMember>
    <dnodes fid="60172">
      <ogr:geometryProperty><gml:Point><gml:coordinates>-0.279162,40.138760</gml:coordinates></gml:Point></ogr:geometryProperty>
      <NODE_ID>60172</NODE_ID>
      <NODE_NAME>MEDNEB2</NODE_NAME>
      <NODE_TYPE>N_A</NODE_TYPE>
      <STATUS>Planned</STATUS>
    </dnodes>
  </gml:featureMember>
  <gml:featureMember>
    <dnodes fid="61149">
      <ogr:geometryProperty><gml:Point><gml:coordinates>-0.278425,40.135742</gml:coordinates></gml:Point></ogr:geometryProperty>
      <NODE_ID>61149</NODE_ID>
      <NODE_NAME>AVCASTJAV</NODE_NAME>
      <NODE_TYPE>client</NODE_TYPE>
      <STATUS>Planned</STATUS>
    </dnodes>
  </gml:featureMember>
  <gml:featureMember>
    <dnodes fid="62538">
      <ogr:geometryProperty><gml:Point><gml:coordinates>-0.089098,39.892287</gml:coordinates></gml:Point></ogr:geometryProperty>
      <NODE_ID>62538</NODE_ID>
      <NODE_NAME>Bur-camionda-42a</NODE_NAME>
      <NODE_TYPE>N_A</NODE_TYPE>
      <STATUS>Planned</STATUS>
    </dnodes>
  </gml:featureMember>
  <gml:featureMember>
    <dnodes fid="62539">
      <ogr:geometryProperty><gml:Point><gml:coordinates>-0.056216,39.877224</gml:coordinates></gml:Point></ogr:geometryProperty>
      <NODE_ID>62539</NODE_ID>
      <NODE_NAME>Bur-camigrau-23a</NODE_NAME>
      <NODE_TYPE>N_A</NODE_TYPE>
      <STATUS>Planned</STATUS>
    </dnodes>
  </gml:featureMember>
  <gml:featureMember>
    <dnodes fid="74382">
      <ogr:geometryProperty><gml:Point><gml:coordinates>-0.280880,40.134823</gml:coordinates></gml:Point></ogr:geometryProperty>
      <NODE_ID>74382</NODE_ID>
      <NODE_NAME>40v</NODE_NAME>
      <NODE_TYPE>client</NODE_TYPE>
      <STATUS>Testing</STATUS>
    </dnodes>
  </gml:featureMember>
</ogr:FeatureCollection>