<?xml version="1.0" encoding="utf-8" ?>
<ogr:FeatureCollection
     xmlns:xsi="http://www.w3c.org/2001/XMLSchema-instance"
     xsi:schemaLocation=". dnodes.xsd"
     xmlns:ogr="http://ogr.maptools.org/"
     xmlns:gml="http://www.opengis.net/gml">
  <gml:boundedBy>
    <gml:Box>
      <gml:coord><gml:X>2.114454</gml:X><gml:Y>42.215560</gml:Y></gml:coord>
      <gml:coord><gml:X>2.178643</gml:X><gml:Y>42.250617</gml:Y></gml:coord>
    </gml:Box>
  </gml:boundedBy>
  <gml:featureMember>
    <dnodes fid="29680">
      <ogr:geometryProperty><gml:Point><gml:coordinates>2.168998,42.223391</gml:coordinates></gml:Point></ogr:geometryProperty>
      <NODE_ID>29680</NODE_ID>
      <NODE_NAME>Cmpdv-Ajuntament</NODE_NAME>
      <NODE_TYPE>N_A</NODE_TYPE>
      <STATUS>Planned</STATUS>
    </dnodes>
  </gml:featureMember>
  <gml:featureMember>
    <dnodes fid="41596">
      <ogr:geometryProperty><gml:Point><gml:coordinates>2.167804,42.224496</gml:coordinates></gml:Point></ogr:geometryProperty>
      <NODE_ID>41596</NODE_ID>
      <NODE_NAME>Cmpdv-FranTrenaAgui</NODE_NAME>
      <NODE_TYPE>N_A</NODE_TYPE>
      <STATUS>Planned</STATUS>
    </dnodes>
  </gml:featureMember>
  <gml:featureMember>
    <dnodes fid="42272">
      <ogr:geometryProperty><gml:Point><gml:coordinates>2.168236,42.224953</gml:coordinates></gml:Point></ogr:geometryProperty>
      <NODE_ID>42272</NODE_ID>
      <NODE_NAME>Cmpdv-SalaDiagonal</NODE_NAME>
      <NODE_TYPE>N_A</NODE_TYPE>
      <STATUS>Planned</STATUS>
    </dnodes>
  </gml:featureMember>
  <gml:featureMember>
    <dnodes fid="29720">
      <ogr:geometryProperty><gml:Point><gml:coordinates>2.164266,42.225803</gml:coordinates></gml:Point></ogr:geometryProperty>
      <NODE_ID>29720</NODE_ID>
      <NODE_NAME>Cmpdv-Cementiri</NODE_NAME>
      <NODE_TYPE>Supernode</NODE_TYPE>
      <STATUS>Working</STATUS>
    </dnodes>
  </gml:featureMember>
  <gml:featureMember>
    <dnodes fid="37603">
      <ogr:geometryProperty><gml:Point><gml:coordinates>2.167041,42.219818</gml:coordinates></gml:Point></ogr:geometryProperty>
      <NODE_ID>37603</NODE_ID>
      <NODE_NAME>Cmpdv-JLordella</NODE_NAME>
      <NODE_TYPE>N_A</NODE_TYPE>
      <STATUS>Planned</STATUS>
    </dnodes>
  </gml:featureMember>
  <gml:featureMember>
    <dnodes fid="41415">
      <ogr:geometryProperty><gml:Point><gml:coordinates>2.163047,42.224762</gml:coordinates></gml:Point></ogr:geometryProperty>
      <NODE_ID>41415</NODE_ID>
      <NODE_NAME>Cmpdv-VistaAlegre16</NODE_NAME>
      <NODE_TYPE>N_A</NODE_TYPE>
      <STATUS>Planned</STATUS>
    </dnodes>
  </gml:featureMember>
  <gml:featureMember>
    <dnodes fid="47566">
      <ogr:geometryProperty><gml:Point><gml:coordinates>2.178643,42.250617</gml:coordinates></gml:Point></ogr:geometryProperty>
      <NODE_ID>47566</NODE_ID>
      <NODE_NAME>Cmpdv-coronas</NODE_NAME>
      <NODE_TYPE>N_A</NODE_TYPE>
      <STATUS>Planned</STATUS>
    </dnodes>
  </gml:featureMember>
  <gml:featureMember>
    <dnodes fid="65754">
      <ogr:geometryProperty><gml:Point><gml:coordinates>2.153521,42.224937</gml:coordinates></gml:Point></ogr:geometryProperty>
      <NODE_ID>65754</NODE_ID>
      <NODE_NAME>Cmpdv-CalCornut</NODE_NAME>
      <NODE_TYPE>N_A</NODE_TYPE>
      <STATUS>Planned</STATUS>
    </dnodes>
  </gml:featureMember>
  <gml:featureMember>
    <dnodes fid="49271">
      <ogr:geometryProperty><gml:Point><gml:coordinates>2.168166,42.221072</gml:coordinates></gml:Point></ogr:geometryProperty>
      <NODE_ID>49271</NODE_ID>
      <NODE_NAME>Cmpdv-Eliseu</NODE_NAME>
      <NODE_TYPE>client</NODE_TYPE>
      <STATUS>Working</STATUS>
    </dnodes>
  </gml:featureMember>
  <gml:featureMember>
    <dnodes fid="52731">
      <ogr:geometryProperty><gml:Point><gml:coordinates>2.168767,42.221310</gml:coordinates></gml:Point></ogr:geometryProperty>
      <NODE_ID>52731</NODE_ID>
      <NODE_NAME>Cmpdv-major34</NODE_NAME>
      <NODE_TYPE>N_A</NODE_TYPE>
      <STATUS>Planned</STATUS>
    </dnodes>
  </gml:featureMember>
  <gml:featureMember>
    <dnodes fid="51093">
      <ogr:geometryProperty><gml:Point><gml:coordinates>2.168496,42.222954</gml:coordinates></gml:Point></ogr:geometryProperty>
      <NODE_ID>51093</NODE_ID>
      <NODE_NAME>Cmpdv-Nasiet</NODE_NAME>
      <NODE_TYPE>client</NODE_TYPE>
      <STATUS>Working</STATUS>
    </dnodes>
  </gml:featureMember>
  <gml:featureMember>
    <dnodes fid="52193">
      <ogr:geometryProperty><gml:Point><gml:coordinates>2.173689,42.222865</gml:coordinates></gml:Point></ogr:geometryProperty>
      <NODE_ID>52193</NODE_ID>
      <NODE_NAME>Cmpdv-TV</NODE_NAME>
      <NODE_TYPE>N_A</NODE_TYPE>
      <STATUS>Planned</STATUS>
    </dnodes>
  </gml:featureMember>
  <gml:featureMember>
    <dnodes fid="58087">
      <ogr:geometryProperty><gml:Point><gml:coordinates>2.131412,42.215560</gml:coordinates></gml:Point></ogr:geometryProperty>
      <NODE_ID>58087</NODE_ID>
      <NODE_NAME>Cmpdv-Perfils</NODE_NAME>
      <NODE_TYPE>N_A</NODE_TYPE>
      <STATUS>Planned</STATUS>
    </dnodes>
  </gml:featureMember>
  <gml:featureMember>
    <dnodes fid="60539">
      <ogr:geometryProperty><gml:Point><gml:coordinates>2.169498,42.221853</gml:coordinates></gml:Point></ogr:geometryProperty>
      <NODE_ID>60539</NODE_ID>
      <NODE_NAME>Cmpdv-Gombren3</NODE_NAME>
      <NODE_TYPE>N_A</NODE_TYPE>
      <STATUS>Planned</STATUS>
    </dnodes>
  </gml:featureMember>
  <gml:featureMember>
    <dnodes fid="60651">
      <ogr:geometryProperty><gml:Point><gml:coordinates>2.167928,42.221229</gml:coordinates></gml:Point></ogr:geometryProperty>
      <NODE_ID>60651</NODE_ID>
      <NODE_NAME>Cmpdv-LLevant2</NODE_NAME>
      <NODE_TYPE>client</NODE_TYPE>
      <STATUS>Working</STATUS>
    </dnodes>
  </gml:featureMember>
  <gml:featureMember>
    <dnodes fid="63573">
      <ogr:geometryProperty><gml:Point><gml:coordinates>2.114454,42.243595</gml:coordinates></gml:Point></ogr:geometryProperty>
      <NODE_ID>63573</NODE_ID>
      <NODE_NAME>Cmpdv-Pujals</NODE_NAME>
      <NODE_TYPE>N_A</NODE_TYPE>
      <STATUS>Planned</STATUS>
    </dnodes>
  </gml:featureMember>
  <gml:featureMember>
    <dnodes fid="64534">
      <ogr:geometryProperty><gml:Point><gml:coordinates>2.167966,42.221186</gml:coordinates></gml:Point></ogr:geometryProperty>
      <NODE_ID>64534</NODE_ID>
      <NODE_NAME>Cmpdv-Llevant2-2</NODE_NAME>
      <NODE_TYPE>N_A</NODE_TYPE>
      <STATUS>Planned</STATUS>
    </dnodes>
  </gml:featureMember>
  <gml:featureMember>
    <dnodes fid="66077">
      <ogr:geometryProperty><gml:Point><gml:coordinates>2.172369,42.223389</gml:coordinates></gml:Point></ogr:geometryProperty>
      <NODE_ID>66077</NODE_ID>
      <NODE_NAME>Cmpdv-Castell16</NODE_NAME>
      <NODE_TYPE>N_A</NODE_TYPE>
      <STATUS>Planned</STATUS>
    </dnodes>
  </gml:featureMember>
  <gml:featureMember>
    <dnodes fid="69113">
      <ogr:geometryProperty><gml:Point><gml:coordinates>2.169553,42.221753</gml:coordinates></gml:Point></ogr:geometryProperty>
      <NODE_ID>69113</NODE_ID>
      <NODE_NAME>Cmpdv-AntonioNieto</NODE_NAME>
      <NODE_TYPE>client</NODE_TYPE>
      <STATUS>Working</STATUS>
    </dnodes>
  </gml:featureMember>
  <gml:featureMember>
    <dnodes fid="76332">
      <ogr:geometryProperty><gml:Point><gml:coordinates>2.167161,42.220218</gml:coordinates></gml:Point></ogr:geometryProperty>
      <NODE_ID>76332</NODE_ID>
      <NODE_NAME>Cmpdv-Guilla</NODE_NAME>
      <NODE_TYPE>client</NODE_TYPE>
      <STATUS>Testing</STATUS>
    </dnodes>
  </gml:featureMember>
</ogr:FeatureCollection>