{"nodes":[{"id":23205,"STATUS":"Planned","weight":23205,"type":"client","name":"IBZcatamaran","coordinates":"1.294659,38.983576"},{"id":23206,"STATUS":"Planned","weight":23206,"type":"ap","name":"IBZatalaiaSantJosep","coordinates":"1.277574,38.915713"},{"id":23211,"STATUS":"Planned","weight":23211,"type":"N_A","name":"StRafel","coordinates":"1.300934,38.981940"},{"id":43133,"STATUS":"Planned","weight":43133,"type":"N_A","name":"Posidonia","coordinates":"1.295614,38.987360"},{"id":37866,"STATUS":"Planned","weight":37866,"type":"N_A","name":"IBZreguero6","coordinates":"1.313596,38.972697"},{"id":41721,"STATUS":"Planned","weight":41721,"type":"N_A","name":"IBZSantRafelDeSaCreu","coordinates":"1.411932,38.955639"},{"id":41392,"STATUS":"Planned","weight":41392,"type":"N_A","name":"IBZsancarlos","coordinates":"1.587560,39.019387"},{"id":48001,"STATUS":"Planned","weight":48001,"type":"N_A","name":"SJEPuntaPinet","coordinates":"1.288281,38.969340"},{"id":49923,"STATUS":"Planned","weight":49923,"type":"N_A","name":"IBZStaGertrudis","coordinates":"1.468066,38.996999"},{"id":51271,"STATUS":"Planned","weight":51271,"type":"N_A","name":"vss","coordinates":"1.434556,38.908807"},{"id":58187,"STATUS":"Planned","weight":58187,"type":"N_A","name":"BZVrdRy","coordinates":"1.433555,38.909427"}],"links":[{"id":42048,"KMS":99.356,"STATUS":"Planned","target":23206,"source":40049,"type":"wds","NODE1_NAME":"AJBenitatxellCumbre","NODE2_NAME":"IBZatalaiaSantJosep","coordinates":"0.159192,38.727059 1.277574,38.915713"}]}