{"nodes":[{"id":69441,"STATUS":"Planned","weight":69441,"type":"N_A","name":"VLLVCSselorioprueba","coordinates":"-5.367523,43.516126"},{"id":72014,"STATUS":"Working","weight":72014,"type":"client","name":"VLLVCSspecialsurf","coordinates":"-5.383201,43.530001"},{"id":74371,"STATUS":"Working","weight":74371,"type":"client","name":"VLLVCSRteCasaAida","coordinates":"-5.384421,43.527685"},{"id":74788,"STATUS":"Working","weight":74788,"type":"client","name":"VLLVCSRodiSLlorenti","coordinates":"-5.379469,43.529606"},{"id":75197,"STATUS":"Planned","weight":75197,"type":"N_A","name":"VLLVCSPiniella15","coordinates":"-5.373502,43.517384"}],"links":[{"id":79023,"KMS":4.12,"STATUS":"Working","target":61748,"source":72014,"type":"ap\/client","NODE1_NAME":"VLLVCSspecialsurf","NODE2_NAME":"VLLVCSPando","coordinates":"-5.383201,43.530001 -5.405932,43.496809"},{"id":79866,"KMS":3.846,"STATUS":"Working","target":61748,"source":74371,"type":"ap\/client","NODE1_NAME":"VLLVCSRteCasaAida","NODE2_NAME":"VLLVCSPando","coordinates":"-5.384421,43.527685 -5.405932,43.496809"},{"id":80840,"KMS":4.226,"STATUS":"Working","target":61748,"source":74788,"type":"ap\/client","NODE1_NAME":"VLLVCSRodiSLlorenti","NODE2_NAME":"VLLVCSPando","coordinates":"-5.379469,43.529606 -5.405932,43.496809"}]}